[{"title":"Yombu","sleeps":12,"bedRooms":4,"bathRooms":3,"halfBaths":3,"area":9867,"minStay":5,"pricePerNight":386,"totalPrice":3986,"rating":4},
{"title":"Feednation","sleeps":13,"bedRooms":1,"bathRooms":3,"halfBaths":4,"area":8404,"minStay":5,"pricePerNight":457,"totalPrice":9207,"rating":2},
{"title":"Youfeed","sleeps":12,"bedRooms":5,"bathRooms":3,"halfBaths":2,"area":9006,"minStay":2,"pricePerNight":658,"totalPrice":6860,"rating":5},
{"title":"Cogilith","sleeps":7,"bedRooms":4,"bathRooms":3,"halfBaths":4,"area":7820,"minStay":3,"pricePerNight":288,"totalPrice":6767,"rating":1},
{"title":"Kazio","sleeps":18,"bedRooms":4,"bathRooms":4,"halfBaths":3,"area":9666,"minStay":4,"pricePerNight":320,"totalPrice":8825,"rating":2},
{"title":"Twitterlist","sleeps":6,"bedRooms":4,"bathRooms":4,"halfBaths":1,"area":7992,"minStay":3,"pricePerNight":317,"totalPrice":8254,"rating":5},
{"title":"Brightdog","sleeps":19,"bedRooms":3,"bathRooms":4,"halfBaths":3,"area":8402,"minStay":5,"pricePerNight":280,"totalPrice":8761,"rating":4},
{"title":"Wordify","sleeps":11,"bedRooms":4,"bathRooms":1,"halfBaths":4,"area":9582,"minStay":2,"pricePerNight":173,"totalPrice":5506,"rating":2},
{"title":"Abata","sleeps":12,"bedRooms":5,"bathRooms":4,"halfBaths":5,"area":8253,"minStay":3,"pricePerNight":348,"totalPrice":6427,"rating":2},
{"title":"Babbleopia","sleeps":2,"bedRooms":3,"bathRooms":4,"halfBaths":4,"area":8200,"minStay":3,"pricePerNight":131,"totalPrice":9039,"rating":4},
{"title":"Avamm","sleeps":5,"bedRooms":2,"bathRooms":3,"halfBaths":3,"area":9446,"minStay":3,"pricePerNight":474,"totalPrice":5352,"rating":3},
{"title":"Quinu","sleeps":11,"bedRooms":2,"bathRooms":2,"halfBaths":5,"area":9288,"minStay":4,"pricePerNight":440,"totalPrice":3652,"rating":1},
{"title":"Photofeed","sleeps":17,"bedRooms":3,"bathRooms":3,"halfBaths":4,"area":7528,"minStay":5,"pricePerNight":689,"totalPrice":8437,"rating":4},
{"title":"Thoughtbeat","sleeps":11,"bedRooms":4,"bathRooms":1,"halfBaths":5,"area":9557,"minStay":5,"pricePerNight":267,"totalPrice":4858,"rating":2},
{"title":"Meevee","sleeps":6,"bedRooms":2,"bathRooms":3,"halfBaths":3,"area":8982,"minStay":5,"pricePerNight":432,"totalPrice":7012,"rating":5},
{"title":"Latz","sleeps":15,"bedRooms":3,"bathRooms":1,"halfBaths":4,"area":8965,"minStay":2,"pricePerNight":113,"totalPrice":4799,"rating":4},
{"title":"Centimia","sleeps":13,"bedRooms":3,"bathRooms":2,"halfBaths":3,"area":9516,"minStay":4,"pricePerNight":508,"totalPrice":5584,"rating":3},
{"title":"Trudeo","sleeps":15,"bedRooms":1,"bathRooms":2,"halfBaths":1,"area":8025,"minStay":2,"pricePerNight":554,"totalPrice":8665,"rating":2},
{"title":"Dazzlesphere","sleeps":1,"bedRooms":4,"bathRooms":3,"halfBaths":4,"area":8032,"minStay":5,"pricePerNight":217,"totalPrice":3565,"rating":2},
{"title":"Quatz","sleeps":19,"bedRooms":3,"bathRooms":3,"halfBaths":2,"area":7694,"minStay":3,"pricePerNight":259,"totalPrice":8911,"rating":3},
{"title":"Gabtune","sleeps":7,"bedRooms":1,"bathRooms":4,"halfBaths":1,"area":8230,"minStay":5,"pricePerNight":439,"totalPrice":5380,"rating":3},
{"title":"Digitube","sleeps":10,"bedRooms":3,"bathRooms":4,"halfBaths":4,"area":8527,"minStay":3,"pricePerNight":473,"totalPrice":9074,"rating":4},
{"title":"Jazzy","sleeps":20,"bedRooms":2,"bathRooms":2,"halfBaths":1,"area":8233,"minStay":4,"pricePerNight":591,"totalPrice":9202,"rating":3},
{"title":"Gabspot","sleeps":13,"bedRooms":1,"bathRooms":2,"halfBaths":4,"area":9283,"minStay":3,"pricePerNight":209,"totalPrice":9575,"rating":3},
{"title":"Voonder","sleeps":9,"bedRooms":1,"bathRooms":4,"halfBaths":3,"area":8687,"minStay":3,"pricePerNight":547,"totalPrice":9098,"rating":3},
{"title":"Meetz","sleeps":13,"bedRooms":1,"bathRooms":3,"halfBaths":2,"area":9458,"minStay":4,"pricePerNight":657,"totalPrice":6419,"rating":3},
{"title":"Buzzdog","sleeps":1,"bedRooms":4,"bathRooms":4,"halfBaths":5,"area":8758,"minStay":4,"pricePerNight":633,"totalPrice":4674,"rating":5},
{"title":"Zoombox","sleeps":7,"bedRooms":3,"bathRooms":3,"halfBaths":2,"area":9643,"minStay":4,"pricePerNight":485,"totalPrice":8640,"rating":1},
{"title":"Voonder","sleeps":14,"bedRooms":3,"bathRooms":3,"halfBaths":1,"area":8205,"minStay":3,"pricePerNight":258,"totalPrice":8889,"rating":5},
{"title":"Feedbug","sleeps":6,"bedRooms":2,"bathRooms":3,"halfBaths":5,"area":8811,"minStay":2,"pricePerNight":415,"totalPrice":5988,"rating":1},
{"title":"Roodel","sleeps":5,"bedRooms":4,"bathRooms":3,"halfBaths":1,"area":8668,"minStay":5,"pricePerNight":415,"totalPrice":6403,"rating":5},
{"title":"Jamia","sleeps":4,"bedRooms":4,"bathRooms":4,"halfBaths":4,"area":9258,"minStay":3,"pricePerNight":667,"totalPrice":6095,"rating":3},
{"title":"Agivu","sleeps":7,"bedRooms":5,"bathRooms":3,"halfBaths":5,"area":8173,"minStay":3,"pricePerNight":446,"totalPrice":8300,"rating":5},
{"title":"Fivespan","sleeps":8,"bedRooms":5,"bathRooms":2,"halfBaths":4,"area":8375,"minStay":2,"pricePerNight":579,"totalPrice":5469,"rating":1},
{"title":"Tazzy","sleeps":20,"bedRooms":5,"bathRooms":4,"halfBaths":2,"area":9951,"minStay":5,"pricePerNight":325,"totalPrice":8264,"rating":2},
{"title":"Chatterpoint","sleeps":11,"bedRooms":3,"bathRooms":1,"halfBaths":1,"area":9125,"minStay":3,"pricePerNight":213,"totalPrice":7433,"rating":2},
{"title":"Snaptags","sleeps":7,"bedRooms":1,"bathRooms":1,"halfBaths":1,"area":8727,"minStay":5,"pricePerNight":325,"totalPrice":6140,"rating":4},
{"title":"Topdrive","sleeps":18,"bedRooms":4,"bathRooms":3,"halfBaths":5,"area":9654,"minStay":5,"pricePerNight":558,"totalPrice":7501,"rating":4},
{"title":"Kazu","sleeps":8,"bedRooms":2,"bathRooms":1,"halfBaths":5,"area":7518,"minStay":4,"pricePerNight":373,"totalPrice":4052,"rating":4},
{"title":"Divape","sleeps":16,"bedRooms":5,"bathRooms":4,"halfBaths":4,"area":9139,"minStay":5,"pricePerNight":257,"totalPrice":4278,"rating":4},
{"title":"Kwilith","sleeps":2,"bedRooms":4,"bathRooms":1,"halfBaths":3,"area":8684,"minStay":5,"pricePerNight":370,"totalPrice":9043,"rating":3},
{"title":"Jatri","sleeps":13,"bedRooms":3,"bathRooms":1,"halfBaths":4,"area":8903,"minStay":3,"pricePerNight":673,"totalPrice":6020,"rating":2},
{"title":"Lazz","sleeps":3,"bedRooms":3,"bathRooms":3,"halfBaths":5,"area":9294,"minStay":5,"pricePerNight":159,"totalPrice":5088,"rating":1},
{"title":"Browsecat","sleeps":7,"bedRooms":3,"bathRooms":1,"halfBaths":2,"area":8436,"minStay":5,"pricePerNight":574,"totalPrice":9029,"rating":2},
{"title":"Yombu","sleeps":1,"bedRooms":4,"bathRooms":1,"halfBaths":5,"area":7558,"minStay":4,"pricePerNight":287,"totalPrice":4266,"rating":5},
{"title":"Photobug","sleeps":2,"bedRooms":3,"bathRooms":1,"halfBaths":5,"area":7864,"minStay":2,"pricePerNight":201,"totalPrice":4286,"rating":3},
{"title":"Zoomlounge","sleeps":17,"bedRooms":4,"bathRooms":4,"halfBaths":3,"area":9571,"minStay":5,"pricePerNight":283,"totalPrice":9112,"rating":5},
{"title":"Thoughtstorm","sleeps":2,"bedRooms":3,"bathRooms":2,"halfBaths":5,"area":8079,"minStay":3,"pricePerNight":528,"totalPrice":3697,"rating":2},
{"title":"Tazz","sleeps":5,"bedRooms":5,"bathRooms":3,"halfBaths":5,"area":9354,"minStay":5,"pricePerNight":458,"totalPrice":5137,"rating":1},
{"title":"Divavu","sleeps":6,"bedRooms":2,"bathRooms":2,"halfBaths":1,"area":9713,"minStay":4,"pricePerNight":411,"totalPrice":8670,"rating":5},
{"title":"Zooxo","sleeps":2,"bedRooms":2,"bathRooms":1,"halfBaths":1,"area":9338,"minStay":5,"pricePerNight":371,"totalPrice":6059,"rating":2},
{"title":"Skiba","sleeps":4,"bedRooms":5,"bathRooms":3,"halfBaths":1,"area":9091,"minStay":4,"pricePerNight":349,"totalPrice":6680,"rating":5},
{"title":"Layo","sleeps":16,"bedRooms":2,"bathRooms":4,"halfBaths":5,"area":7975,"minStay":3,"pricePerNight":291,"totalPrice":9976,"rating":2},
{"title":"Vinder","sleeps":14,"bedRooms":3,"bathRooms":2,"halfBaths":4,"area":8181,"minStay":3,"pricePerNight":511,"totalPrice":9181,"rating":3},
{"title":"Buzzbean","sleeps":1,"bedRooms":5,"bathRooms":1,"halfBaths":4,"area":7716,"minStay":3,"pricePerNight":106,"totalPrice":4921,"rating":5},
{"title":"Skyble","sleeps":19,"bedRooms":4,"bathRooms":1,"halfBaths":4,"area":9412,"minStay":5,"pricePerNight":386,"totalPrice":3233,"rating":1},
{"title":"Fivebridge","sleeps":20,"bedRooms":5,"bathRooms":2,"halfBaths":1,"area":9158,"minStay":3,"pricePerNight":532,"totalPrice":6304,"rating":2},
{"title":"Fivebridge","sleeps":17,"bedRooms":5,"bathRooms":2,"halfBaths":2,"area":8079,"minStay":3,"pricePerNight":344,"totalPrice":7546,"rating":3},
{"title":"Thoughtsphere","sleeps":6,"bedRooms":3,"bathRooms":1,"halfBaths":4,"area":8121,"minStay":2,"pricePerNight":212,"totalPrice":9837,"rating":3},
{"title":"Thoughtbeat","sleeps":8,"bedRooms":1,"bathRooms":4,"halfBaths":3,"area":9221,"minStay":3,"pricePerNight":575,"totalPrice":6148,"rating":3},
{"title":"Demimbu","sleeps":17,"bedRooms":3,"bathRooms":2,"halfBaths":4,"area":8681,"minStay":4,"pricePerNight":393,"totalPrice":6476,"rating":1},
{"title":"InnoZ","sleeps":10,"bedRooms":3,"bathRooms":2,"halfBaths":4,"area":7972,"minStay":2,"pricePerNight":357,"totalPrice":6708,"rating":4},
{"title":"Mybuzz","sleeps":19,"bedRooms":5,"bathRooms":3,"halfBaths":3,"area":8718,"minStay":2,"pricePerNight":189,"totalPrice":7178,"rating":1},
{"title":"Twiyo","sleeps":16,"bedRooms":3,"bathRooms":1,"halfBaths":1,"area":8808,"minStay":2,"pricePerNight":675,"totalPrice":4428,"rating":5},
{"title":"Tanoodle","sleeps":8,"bedRooms":2,"bathRooms":4,"halfBaths":4,"area":9389,"minStay":5,"pricePerNight":150,"totalPrice":3824,"rating":1},
{"title":"Mymm","sleeps":3,"bedRooms":5,"bathRooms":2,"halfBaths":3,"area":8604,"minStay":2,"pricePerNight":416,"totalPrice":6592,"rating":1},
{"title":"Skinder","sleeps":4,"bedRooms":4,"bathRooms":4,"halfBaths":2,"area":9732,"minStay":5,"pricePerNight":295,"totalPrice":6090,"rating":3},
{"title":"Meejo","sleeps":7,"bedRooms":1,"bathRooms":4,"halfBaths":2,"area":7642,"minStay":4,"pricePerNight":244,"totalPrice":9226,"rating":5},
{"title":"Edgeclub","sleeps":15,"bedRooms":5,"bathRooms":1,"halfBaths":5,"area":9695,"minStay":5,"pricePerNight":117,"totalPrice":6098,"rating":3},
{"title":"Wordtune","sleeps":15,"bedRooms":1,"bathRooms":3,"halfBaths":3,"area":9195,"minStay":5,"pricePerNight":467,"totalPrice":3994,"rating":1},
{"title":"Tagpad","sleeps":15,"bedRooms":1,"bathRooms":4,"halfBaths":4,"area":9592,"minStay":3,"pricePerNight":614,"totalPrice":7990,"rating":2},
{"title":"Einti","sleeps":12,"bedRooms":4,"bathRooms":3,"halfBaths":2,"area":8783,"minStay":3,"pricePerNight":343,"totalPrice":4371,"rating":4},
{"title":"Wikido","sleeps":15,"bedRooms":1,"bathRooms":4,"halfBaths":3,"area":9863,"minStay":5,"pricePerNight":200,"totalPrice":3715,"rating":1},
{"title":"Buzzdog","sleeps":1,"bedRooms":3,"bathRooms":2,"halfBaths":1,"area":8369,"minStay":3,"pricePerNight":688,"totalPrice":5371,"rating":5},
{"title":"Wikido","sleeps":11,"bedRooms":5,"bathRooms":3,"halfBaths":2,"area":9057,"minStay":4,"pricePerNight":563,"totalPrice":5887,"rating":2},
{"title":"Topicblab","sleeps":13,"bedRooms":1,"bathRooms":3,"halfBaths":4,"area":8602,"minStay":4,"pricePerNight":683,"totalPrice":9147,"rating":4},
{"title":"Meedoo","sleeps":16,"bedRooms":5,"bathRooms":4,"halfBaths":3,"area":8591,"minStay":3,"pricePerNight":559,"totalPrice":5034,"rating":4},
{"title":"Gigazoom","sleeps":20,"bedRooms":4,"bathRooms":2,"halfBaths":4,"area":8642,"minStay":3,"pricePerNight":483,"totalPrice":6326,"rating":1},
{"title":"Camimbo","sleeps":14,"bedRooms":1,"bathRooms":2,"halfBaths":1,"area":9137,"minStay":2,"pricePerNight":346,"totalPrice":5953,"rating":2},
{"title":"Twitterworks","sleeps":6,"bedRooms":3,"bathRooms":4,"halfBaths":4,"area":8604,"minStay":2,"pricePerNight":450,"totalPrice":9607,"rating":3},
{"title":"Wordware","sleeps":3,"bedRooms":3,"bathRooms":1,"halfBaths":2,"area":7657,"minStay":5,"pricePerNight":330,"totalPrice":9858,"rating":5},
{"title":"Voolia","sleeps":19,"bedRooms":3,"bathRooms":4,"halfBaths":1,"area":9280,"minStay":3,"pricePerNight":470,"totalPrice":4797,"rating":5},
{"title":"Eidel","sleeps":3,"bedRooms":3,"bathRooms":4,"halfBaths":2,"area":9707,"minStay":2,"pricePerNight":674,"totalPrice":7341,"rating":3},
{"title":"Meezzy","sleeps":18,"bedRooms":1,"bathRooms":1,"halfBaths":2,"area":8401,"minStay":5,"pricePerNight":218,"totalPrice":5629,"rating":1},
{"title":"Shuffletag","sleeps":10,"bedRooms":3,"bathRooms":2,"halfBaths":1,"area":8079,"minStay":2,"pricePerNight":483,"totalPrice":7354,"rating":4},
{"title":"Eimbee","sleeps":16,"bedRooms":4,"bathRooms":2,"halfBaths":1,"area":9073,"minStay":5,"pricePerNight":141,"totalPrice":4291,"rating":5},
{"title":"Gigaclub","sleeps":20,"bedRooms":5,"bathRooms":3,"halfBaths":5,"area":7843,"minStay":3,"pricePerNight":494,"totalPrice":9271,"rating":1},
{"title":"Dynabox","sleeps":7,"bedRooms":1,"bathRooms":1,"halfBaths":5,"area":7774,"minStay":5,"pricePerNight":381,"totalPrice":3092,"rating":1},
{"title":"Brainsphere","sleeps":6,"bedRooms":2,"bathRooms":4,"halfBaths":5,"area":7592,"minStay":2,"pricePerNight":443,"totalPrice":5821,"rating":1},
{"title":"Dabtype","sleeps":8,"bedRooms":3,"bathRooms":3,"halfBaths":1,"area":9313,"minStay":4,"pricePerNight":203,"totalPrice":5338,"rating":5},
{"title":"Topiczoom","sleeps":8,"bedRooms":4,"bathRooms":1,"halfBaths":2,"area":7910,"minStay":2,"pricePerNight":530,"totalPrice":5377,"rating":2},
{"title":"Wordtune","sleeps":20,"bedRooms":1,"bathRooms":3,"halfBaths":1,"area":7805,"minStay":4,"pricePerNight":631,"totalPrice":5765,"rating":5},
{"title":"Oyonder","sleeps":20,"bedRooms":4,"bathRooms":1,"halfBaths":1,"area":7690,"minStay":4,"pricePerNight":540,"totalPrice":9472,"rating":5},
{"title":"Agivu","sleeps":9,"bedRooms":2,"bathRooms":2,"halfBaths":3,"area":7651,"minStay":4,"pricePerNight":659,"totalPrice":5879,"rating":3},
{"title":"Centidel","sleeps":6,"bedRooms":4,"bathRooms":4,"halfBaths":4,"area":9235,"minStay":4,"pricePerNight":598,"totalPrice":8238,"rating":3},
{"title":"Gabtune","sleeps":8,"bedRooms":2,"bathRooms":4,"halfBaths":3,"area":7538,"minStay":4,"pricePerNight":117,"totalPrice":3210,"rating":2},
{"title":"Wikizz","sleeps":20,"bedRooms":1,"bathRooms":3,"halfBaths":5,"area":8233,"minStay":4,"pricePerNight":162,"totalPrice":7850,"rating":3},
{"title":"Blogpad","sleeps":8,"bedRooms":4,"bathRooms":1,"halfBaths":5,"area":9732,"minStay":4,"pricePerNight":678,"totalPrice":5182,"rating":1},
{"title":"Zoomdog","sleeps":3,"bedRooms":1,"bathRooms":1,"halfBaths":4,"area":8966,"minStay":4,"pricePerNight":657,"totalPrice":5409,"rating":2},
{"title":"Dabvine","sleeps":15,"bedRooms":1,"bathRooms":1,"halfBaths":3,"area":9962,"minStay":4,"pricePerNight":111,"totalPrice":6566,"rating":5},
{"title":"Zoomcast","sleeps":13,"bedRooms":3,"bathRooms":1,"halfBaths":2,"area":9182,"minStay":2,"pricePerNight":268,"totalPrice":4547,"rating":5},
{"title":"Yakidoo","sleeps":20,"bedRooms":4,"bathRooms":3,"halfBaths":4,"area":9006,"minStay":2,"pricePerNight":326,"totalPrice":6222,"rating":3},
{"title":"Mudo","sleeps":4,"bedRooms":2,"bathRooms":4,"halfBaths":3,"area":8520,"minStay":2,"pricePerNight":691,"totalPrice":4479,"rating":1},
{"title":"Browsezoom","sleeps":19,"bedRooms":3,"bathRooms":4,"halfBaths":5,"area":9981,"minStay":4,"pricePerNight":201,"totalPrice":7746,"rating":5},
{"title":"Gigabox","sleeps":14,"bedRooms":3,"bathRooms":2,"halfBaths":4,"area":8912,"minStay":5,"pricePerNight":133,"totalPrice":8829,"rating":4},
{"title":"Yombu","sleeps":6,"bedRooms":4,"bathRooms":1,"halfBaths":5,"area":9984,"minStay":5,"pricePerNight":541,"totalPrice":9105,"rating":3},
{"title":"Tavu","sleeps":11,"bedRooms":2,"bathRooms":3,"halfBaths":3,"area":9937,"minStay":4,"pricePerNight":606,"totalPrice":8249,"rating":2},
{"title":"Latz","sleeps":1,"bedRooms":4,"bathRooms":1,"halfBaths":3,"area":7678,"minStay":4,"pricePerNight":124,"totalPrice":9609,"rating":2},
{"title":"Mynte","sleeps":18,"bedRooms":2,"bathRooms":1,"halfBaths":4,"area":9371,"minStay":3,"pricePerNight":142,"totalPrice":6374,"rating":5},
{"title":"Realblab","sleeps":6,"bedRooms":4,"bathRooms":1,"halfBaths":1,"area":9221,"minStay":4,"pricePerNight":377,"totalPrice":4664,"rating":5},
{"title":"Miboo","sleeps":6,"bedRooms":1,"bathRooms":3,"halfBaths":5,"area":9921,"minStay":3,"pricePerNight":552,"totalPrice":4426,"rating":4},
{"title":"Dabvine","sleeps":9,"bedRooms":3,"bathRooms":2,"halfBaths":4,"area":9113,"minStay":4,"pricePerNight":157,"totalPrice":4756,"rating":2},
{"title":"Myworks","sleeps":9,"bedRooms":1,"bathRooms":1,"halfBaths":4,"area":7728,"minStay":5,"pricePerNight":541,"totalPrice":9058,"rating":3},
{"title":"Dablist","sleeps":20,"bedRooms":4,"bathRooms":4,"halfBaths":5,"area":8693,"minStay":4,"pricePerNight":389,"totalPrice":7186,"rating":1},
{"title":"Flipstorm","sleeps":7,"bedRooms":4,"bathRooms":1,"halfBaths":3,"area":9743,"minStay":4,"pricePerNight":116,"totalPrice":7972,"rating":2},
{"title":"Bubbletube","sleeps":12,"bedRooms":3,"bathRooms":1,"halfBaths":1,"area":9580,"minStay":5,"pricePerNight":690,"totalPrice":6008,"rating":4},
{"title":"Voomm","sleeps":7,"bedRooms":5,"bathRooms":3,"halfBaths":2,"area":8281,"minStay":5,"pricePerNight":416,"totalPrice":8218,"rating":2},
{"title":"Divanoodle","sleeps":6,"bedRooms":3,"bathRooms":2,"halfBaths":4,"area":8264,"minStay":4,"pricePerNight":673,"totalPrice":9960,"rating":5},
{"title":"Voomm","sleeps":9,"bedRooms":1,"bathRooms":4,"halfBaths":4,"area":7898,"minStay":4,"pricePerNight":131,"totalPrice":5521,"rating":5},
{"title":"Quatz","sleeps":17,"bedRooms":2,"bathRooms":4,"halfBaths":5,"area":8269,"minStay":4,"pricePerNight":445,"totalPrice":5370,"rating":2},
{"title":"Twitterworks","sleeps":19,"bedRooms":2,"bathRooms":1,"halfBaths":5,"area":8872,"minStay":5,"pricePerNight":487,"totalPrice":4720,"rating":4},
{"title":"Babblestorm","sleeps":2,"bedRooms":1,"bathRooms":3,"halfBaths":1,"area":8168,"minStay":5,"pricePerNight":458,"totalPrice":9776,"rating":5},
{"title":"Buzzster","sleeps":3,"bedRooms":1,"bathRooms":4,"halfBaths":2,"area":8504,"minStay":5,"pricePerNight":226,"totalPrice":3094,"rating":4},
{"title":"Zoomzone","sleeps":19,"bedRooms":5,"bathRooms":2,"halfBaths":2,"area":8757,"minStay":4,"pricePerNight":225,"totalPrice":6564,"rating":1},
{"title":"Babbleopia","sleeps":13,"bedRooms":2,"bathRooms":3,"halfBaths":1,"area":7696,"minStay":4,"pricePerNight":366,"totalPrice":4958,"rating":4},
{"title":"Vinte","sleeps":11,"bedRooms":4,"bathRooms":2,"halfBaths":3,"area":9860,"minStay":2,"pricePerNight":530,"totalPrice":7371,"rating":4},
{"title":"Zoonoodle","sleeps":16,"bedRooms":5,"bathRooms":2,"halfBaths":2,"area":8772,"minStay":3,"pricePerNight":271,"totalPrice":5472,"rating":2},
{"title":"Kamba","sleeps":1,"bedRooms":1,"bathRooms":2,"halfBaths":4,"area":9818,"minStay":3,"pricePerNight":156,"totalPrice":9246,"rating":1},
{"title":"Leexo","sleeps":4,"bedRooms":3,"bathRooms":1,"halfBaths":1,"area":8454,"minStay":2,"pricePerNight":337,"totalPrice":6424,"rating":4},
{"title":"Gabspot","sleeps":10,"bedRooms":2,"bathRooms":4,"halfBaths":1,"area":8116,"minStay":3,"pricePerNight":472,"totalPrice":6459,"rating":1},
{"title":"Izio","sleeps":10,"bedRooms":5,"bathRooms":1,"halfBaths":1,"area":9976,"minStay":5,"pricePerNight":346,"totalPrice":3056,"rating":1},
{"title":"Topicshots","sleeps":1,"bedRooms":1,"bathRooms":3,"halfBaths":5,"area":8285,"minStay":3,"pricePerNight":471,"totalPrice":6680,"rating":3},
{"title":"Edgetag","sleeps":11,"bedRooms":5,"bathRooms":3,"halfBaths":2,"area":9973,"minStay":3,"pricePerNight":123,"totalPrice":6317,"rating":2},
{"title":"Skinder","sleeps":17,"bedRooms":5,"bathRooms":1,"halfBaths":3,"area":9033,"minStay":5,"pricePerNight":676,"totalPrice":9490,"rating":3},
{"title":"Voomm","sleeps":20,"bedRooms":2,"bathRooms":4,"halfBaths":5,"area":9129,"minStay":5,"pricePerNight":382,"totalPrice":6200,"rating":5},
{"title":"Vitz","sleeps":18,"bedRooms":3,"bathRooms":3,"halfBaths":5,"area":9235,"minStay":5,"pricePerNight":587,"totalPrice":5806,"rating":4},
{"title":"Edgeify","sleeps":20,"bedRooms":5,"bathRooms":2,"halfBaths":3,"area":9785,"minStay":2,"pricePerNight":524,"totalPrice":8201,"rating":3},
{"title":"Jetpulse","sleeps":7,"bedRooms":3,"bathRooms":4,"halfBaths":4,"area":7673,"minStay":4,"pricePerNight":238,"totalPrice":8009,"rating":4},
{"title":"Feedmix","sleeps":8,"bedRooms":1,"bathRooms":3,"halfBaths":2,"area":7774,"minStay":4,"pricePerNight":216,"totalPrice":3066,"rating":3},
{"title":"Pixonyx","sleeps":6,"bedRooms":3,"bathRooms":1,"halfBaths":3,"area":7957,"minStay":2,"pricePerNight":576,"totalPrice":8125,"rating":4},
{"title":"Yakijo","sleeps":17,"bedRooms":2,"bathRooms":1,"halfBaths":1,"area":9379,"minStay":2,"pricePerNight":444,"totalPrice":8044,"rating":4},
{"title":"Jaxworks","sleeps":19,"bedRooms":2,"bathRooms":4,"halfBaths":3,"area":9388,"minStay":3,"pricePerNight":105,"totalPrice":6562,"rating":4},
{"title":"Layo","sleeps":18,"bedRooms":2,"bathRooms":2,"halfBaths":1,"area":8972,"minStay":5,"pricePerNight":117,"totalPrice":6617,"rating":1},
{"title":"Yambee","sleeps":7,"bedRooms":1,"bathRooms":1,"halfBaths":4,"area":8228,"minStay":2,"pricePerNight":588,"totalPrice":4082,"rating":4},
{"title":"Edgeblab","sleeps":1,"bedRooms":4,"bathRooms":1,"halfBaths":3,"area":8787,"minStay":3,"pricePerNight":545,"totalPrice":9399,"rating":3},
{"title":"Eazzy","sleeps":1,"bedRooms":5,"bathRooms":4,"halfBaths":1,"area":7742,"minStay":3,"pricePerNight":461,"totalPrice":9040,"rating":4},
{"title":"Podcat","sleeps":8,"bedRooms":1,"bathRooms":1,"halfBaths":1,"area":7948,"minStay":3,"pricePerNight":532,"totalPrice":3550,"rating":3},
{"title":"Layo","sleeps":3,"bedRooms":3,"bathRooms":3,"halfBaths":3,"area":8721,"minStay":5,"pricePerNight":384,"totalPrice":3186,"rating":1},
{"title":"Brainbox","sleeps":13,"bedRooms":4,"bathRooms":2,"halfBaths":3,"area":8831,"minStay":3,"pricePerNight":161,"totalPrice":4386,"rating":2},
{"title":"Flashpoint","sleeps":4,"bedRooms":4,"bathRooms":1,"halfBaths":3,"area":8407,"minStay":5,"pricePerNight":574,"totalPrice":5161,"rating":5},
{"title":"Mycat","sleeps":8,"bedRooms":5,"bathRooms":3,"halfBaths":5,"area":9206,"minStay":5,"pricePerNight":420,"totalPrice":4458,"rating":4},
{"title":"Shufflebeat","sleeps":16,"bedRooms":3,"bathRooms":4,"halfBaths":5,"area":8859,"minStay":3,"pricePerNight":510,"totalPrice":9704,"rating":1},
{"title":"Meevee","sleeps":9,"bedRooms":2,"bathRooms":3,"halfBaths":5,"area":9533,"minStay":3,"pricePerNight":423,"totalPrice":8169,"rating":2},
{"title":"Jabberbean","sleeps":2,"bedRooms":3,"bathRooms":3,"halfBaths":3,"area":9143,"minStay":3,"pricePerNight":513,"totalPrice":8925,"rating":5},
{"title":"Thoughtstorm","sleeps":3,"bedRooms":1,"bathRooms":2,"halfBaths":1,"area":8133,"minStay":4,"pricePerNight":274,"totalPrice":9363,"rating":4},
{"title":"Midel","sleeps":20,"bedRooms":5,"bathRooms":4,"halfBaths":4,"area":9121,"minStay":5,"pricePerNight":395,"totalPrice":6939,"rating":4},
{"title":"Gabtune","sleeps":9,"bedRooms":4,"bathRooms":2,"halfBaths":3,"area":8674,"minStay":3,"pricePerNight":410,"totalPrice":3818,"rating":5},
{"title":"Buzzshare","sleeps":18,"bedRooms":3,"bathRooms":4,"halfBaths":5,"area":8328,"minStay":4,"pricePerNight":101,"totalPrice":9270,"rating":3},
{"title":"Twitterlist","sleeps":2,"bedRooms":5,"bathRooms":1,"halfBaths":5,"area":9544,"minStay":5,"pricePerNight":103,"totalPrice":4632,"rating":3},
{"title":"Photojam","sleeps":2,"bedRooms":2,"bathRooms":1,"halfBaths":1,"area":9245,"minStay":5,"pricePerNight":149,"totalPrice":4445,"rating":5},
{"title":"Shuffledrive","sleeps":3,"bedRooms":1,"bathRooms":2,"halfBaths":5,"area":8432,"minStay":4,"pricePerNight":228,"totalPrice":6940,"rating":3},
{"title":"InnoZ","sleeps":19,"bedRooms":1,"bathRooms":3,"halfBaths":3,"area":8244,"minStay":2,"pricePerNight":281,"totalPrice":3140,"rating":1},
{"title":"Teklist","sleeps":5,"bedRooms":2,"bathRooms":2,"halfBaths":5,"area":9147,"minStay":5,"pricePerNight":239,"totalPrice":6596,"rating":5},
{"title":"Skynoodle","sleeps":5,"bedRooms":4,"bathRooms":1,"halfBaths":3,"area":7977,"minStay":5,"pricePerNight":495,"totalPrice":5440,"rating":1},
{"title":"Mynte","sleeps":7,"bedRooms":2,"bathRooms":1,"halfBaths":2,"area":9255,"minStay":5,"pricePerNight":568,"totalPrice":5727,"rating":1},
{"title":"Plajo","sleeps":20,"bedRooms":2,"bathRooms":1,"halfBaths":5,"area":8953,"minStay":3,"pricePerNight":211,"totalPrice":9286,"rating":4},
{"title":"Zoonder","sleeps":12,"bedRooms":1,"bathRooms":4,"halfBaths":4,"area":7916,"minStay":5,"pricePerNight":624,"totalPrice":9429,"rating":3},
{"title":"Rhyzio","sleeps":18,"bedRooms":5,"bathRooms":3,"halfBaths":5,"area":9435,"minStay":4,"pricePerNight":620,"totalPrice":7149,"rating":1},
{"title":"Photojam","sleeps":6,"bedRooms":5,"bathRooms":4,"halfBaths":2,"area":7506,"minStay":2,"pricePerNight":562,"totalPrice":4777,"rating":2},
{"title":"Gigazoom","sleeps":1,"bedRooms":3,"bathRooms":4,"halfBaths":2,"area":9199,"minStay":4,"pricePerNight":318,"totalPrice":3409,"rating":1},
{"title":"Demizz","sleeps":6,"bedRooms":1,"bathRooms":2,"halfBaths":1,"area":7606,"minStay":4,"pricePerNight":332,"totalPrice":3414,"rating":2},
{"title":"Photobug","sleeps":10,"bedRooms":3,"bathRooms":1,"halfBaths":4,"area":9554,"minStay":5,"pricePerNight":533,"totalPrice":5283,"rating":1},
{"title":"Voolia","sleeps":20,"bedRooms":4,"bathRooms":2,"halfBaths":1,"area":9121,"minStay":4,"pricePerNight":493,"totalPrice":4480,"rating":1},
{"title":"Edgepulse","sleeps":18,"bedRooms":1,"bathRooms":3,"halfBaths":1,"area":8270,"minStay":3,"pricePerNight":297,"totalPrice":7947,"rating":3},
{"title":"Topdrive","sleeps":19,"bedRooms":5,"bathRooms":1,"halfBaths":3,"area":9631,"minStay":5,"pricePerNight":116,"totalPrice":3780,"rating":5},
{"title":"Voonix","sleeps":2,"bedRooms":4,"bathRooms":2,"halfBaths":1,"area":7885,"minStay":3,"pricePerNight":327,"totalPrice":4778,"rating":4},
{"title":"Ailane","sleeps":1,"bedRooms":1,"bathRooms":3,"halfBaths":4,"area":9529,"minStay":4,"pricePerNight":317,"totalPrice":9354,"rating":4},
{"title":"Browseblab","sleeps":6,"bedRooms":2,"bathRooms":4,"halfBaths":1,"area":9436,"minStay":4,"pricePerNight":551,"totalPrice":6791,"rating":2},
{"title":"Wikizz","sleeps":6,"bedRooms":5,"bathRooms":1,"halfBaths":1,"area":7725,"minStay":3,"pricePerNight":492,"totalPrice":6200,"rating":4},
{"title":"Skidoo","sleeps":16,"bedRooms":3,"bathRooms":3,"halfBaths":3,"area":9431,"minStay":5,"pricePerNight":678,"totalPrice":5086,"rating":3},
{"title":"Tanoodle","sleeps":16,"bedRooms":2,"bathRooms":3,"halfBaths":2,"area":7629,"minStay":5,"pricePerNight":553,"totalPrice":9142,"rating":5},
{"title":"Skyba","sleeps":5,"bedRooms":3,"bathRooms":3,"halfBaths":3,"area":9443,"minStay":3,"pricePerNight":453,"totalPrice":5934,"rating":1},
{"title":"Livefish","sleeps":17,"bedRooms":2,"bathRooms":3,"halfBaths":1,"area":9908,"minStay":3,"pricePerNight":440,"totalPrice":6017,"rating":1},
{"title":"Quire","sleeps":5,"bedRooms":4,"bathRooms":3,"halfBaths":1,"area":8855,"minStay":2,"pricePerNight":550,"totalPrice":8744,"rating":4},
{"title":"Oyoloo","sleeps":15,"bedRooms":2,"bathRooms":4,"halfBaths":3,"area":9885,"minStay":5,"pricePerNight":467,"totalPrice":3764,"rating":1},
{"title":"Shufflester","sleeps":14,"bedRooms":1,"bathRooms":2,"halfBaths":5,"area":9473,"minStay":5,"pricePerNight":672,"totalPrice":7597,"rating":1},
{"title":"Youspan","sleeps":11,"bedRooms":1,"bathRooms":2,"halfBaths":1,"area":8787,"minStay":4,"pricePerNight":427,"totalPrice":7701,"rating":3},
{"title":"Quatz","sleeps":11,"bedRooms":3,"bathRooms":3,"halfBaths":2,"area":7519,"minStay":5,"pricePerNight":228,"totalPrice":9444,"rating":3},
{"title":"Roombo","sleeps":4,"bedRooms":3,"bathRooms":4,"halfBaths":3,"area":9121,"minStay":3,"pricePerNight":188,"totalPrice":4938,"rating":3},
{"title":"Jaxbean","sleeps":10,"bedRooms":1,"bathRooms":2,"halfBaths":3,"area":9937,"minStay":3,"pricePerNight":401,"totalPrice":9770,"rating":4},
{"title":"Skimia","sleeps":18,"bedRooms":1,"bathRooms":2,"halfBaths":4,"area":7547,"minStay":5,"pricePerNight":530,"totalPrice":8518,"rating":5},
{"title":"Twitterbridge","sleeps":11,"bedRooms":5,"bathRooms":2,"halfBaths":3,"area":8475,"minStay":3,"pricePerNight":699,"totalPrice":9311,"rating":3},
{"title":"Gabtune","sleeps":7,"bedRooms":5,"bathRooms":4,"halfBaths":4,"area":9331,"minStay":3,"pricePerNight":618,"totalPrice":4956,"rating":5},
{"title":"Twitterworks","sleeps":17,"bedRooms":3,"bathRooms":3,"halfBaths":1,"area":7803,"minStay":4,"pricePerNight":402,"totalPrice":6849,"rating":4},
{"title":"Linktype","sleeps":19,"bedRooms":5,"bathRooms":3,"halfBaths":2,"area":9390,"minStay":4,"pricePerNight":317,"totalPrice":8711,"rating":4},
{"title":"Oyoba","sleeps":7,"bedRooms":1,"bathRooms":3,"halfBaths":2,"area":9639,"minStay":2,"pricePerNight":130,"totalPrice":8911,"rating":1},
{"title":"Jetpulse","sleeps":11,"bedRooms":5,"bathRooms":1,"halfBaths":3,"area":7928,"minStay":2,"pricePerNight":624,"totalPrice":4360,"rating":2},
{"title":"Gigabox","sleeps":20,"bedRooms":4,"bathRooms":4,"halfBaths":3,"area":7508,"minStay":4,"pricePerNight":624,"totalPrice":3770,"rating":4},
{"title":"Aibox","sleeps":2,"bedRooms":4,"bathRooms":2,"halfBaths":2,"area":9363,"minStay":5,"pricePerNight":502,"totalPrice":8055,"rating":4},
{"title":"Avamm","sleeps":19,"bedRooms":3,"bathRooms":2,"halfBaths":1,"area":8521,"minStay":2,"pricePerNight":538,"totalPrice":4194,"rating":5},
{"title":"Gigashots","sleeps":4,"bedRooms":5,"bathRooms":4,"halfBaths":4,"area":8151,"minStay":3,"pricePerNight":678,"totalPrice":8329,"rating":5},
{"title":"Skyble","sleeps":9,"bedRooms":4,"bathRooms":4,"halfBaths":5,"area":8093,"minStay":4,"pricePerNight":420,"totalPrice":6848,"rating":4},
{"title":"Tambee","sleeps":15,"bedRooms":5,"bathRooms":2,"halfBaths":1,"area":8696,"minStay":4,"pricePerNight":350,"totalPrice":6175,"rating":4},
{"title":"Skyndu","sleeps":13,"bedRooms":1,"bathRooms":2,"halfBaths":4,"area":9321,"minStay":5,"pricePerNight":264,"totalPrice":3373,"rating":2},
{"title":"Eadel","sleeps":7,"bedRooms":3,"bathRooms":2,"halfBaths":2,"area":9661,"minStay":5,"pricePerNight":170,"totalPrice":6976,"rating":1},
{"title":"Skalith","sleeps":8,"bedRooms":4,"bathRooms":3,"halfBaths":1,"area":9833,"minStay":2,"pricePerNight":267,"totalPrice":8769,"rating":1},
{"title":"Pixoboo","sleeps":6,"bedRooms":2,"bathRooms":3,"halfBaths":1,"area":8492,"minStay":2,"pricePerNight":131,"totalPrice":4027,"rating":1},
{"title":"Buzzster","sleeps":2,"bedRooms":5,"bathRooms":4,"halfBaths":1,"area":9979,"minStay":2,"pricePerNight":108,"totalPrice":9124,"rating":4},
{"title":"Skynoodle","sleeps":19,"bedRooms":3,"bathRooms":3,"halfBaths":2,"area":8670,"minStay":3,"pricePerNight":142,"totalPrice":7110,"rating":2},
{"title":"Camido","sleeps":8,"bedRooms":2,"bathRooms":4,"halfBaths":4,"area":7901,"minStay":3,"pricePerNight":306,"totalPrice":7548,"rating":3},
{"title":"Fanoodle","sleeps":1,"bedRooms":3,"bathRooms":2,"halfBaths":3,"area":8279,"minStay":4,"pricePerNight":160,"totalPrice":8318,"rating":5},
{"title":"Mynte","sleeps":11,"bedRooms":1,"bathRooms":1,"halfBaths":2,"area":8405,"minStay":4,"pricePerNight":481,"totalPrice":8420,"rating":1},
{"title":"Topicware","sleeps":7,"bedRooms":5,"bathRooms":4,"halfBaths":1,"area":8897,"minStay":3,"pricePerNight":457,"totalPrice":9589,"rating":4},
{"title":"Linklinks","sleeps":12,"bedRooms":1,"bathRooms":3,"halfBaths":2,"area":9685,"minStay":2,"pricePerNight":111,"totalPrice":7094,"rating":3},
{"title":"Wordware","sleeps":3,"bedRooms":1,"bathRooms":3,"halfBaths":1,"area":8216,"minStay":3,"pricePerNight":210,"totalPrice":3513,"rating":1},
{"title":"Izio","sleeps":19,"bedRooms":3,"bathRooms":4,"halfBaths":4,"area":9909,"minStay":3,"pricePerNight":289,"totalPrice":6828,"rating":4},
{"title":"Quamba","sleeps":16,"bedRooms":1,"bathRooms":4,"halfBaths":1,"area":8790,"minStay":4,"pricePerNight":461,"totalPrice":9081,"rating":2},
{"title":"Linktype","sleeps":3,"bedRooms":5,"bathRooms":1,"halfBaths":2,"area":9031,"minStay":5,"pricePerNight":370,"totalPrice":8130,"rating":4},
{"title":"Avaveo","sleeps":7,"bedRooms":4,"bathRooms":3,"halfBaths":1,"area":7516,"minStay":2,"pricePerNight":282,"totalPrice":9564,"rating":2},
{"title":"Jatri","sleeps":15,"bedRooms":5,"bathRooms":1,"halfBaths":2,"area":9191,"minStay":3,"pricePerNight":479,"totalPrice":5501,"rating":3},
{"title":"Mymm","sleeps":10,"bedRooms":3,"bathRooms":1,"halfBaths":3,"area":8106,"minStay":5,"pricePerNight":581,"totalPrice":9657,"rating":3},
{"title":"Topicware","sleeps":9,"bedRooms":3,"bathRooms":1,"halfBaths":1,"area":8915,"minStay":5,"pricePerNight":626,"totalPrice":8704,"rating":2},
{"title":"Linkbuzz","sleeps":13,"bedRooms":3,"bathRooms":4,"halfBaths":2,"area":7792,"minStay":4,"pricePerNight":118,"totalPrice":6521,"rating":1},
{"title":"Camido","sleeps":14,"bedRooms":4,"bathRooms":2,"halfBaths":1,"area":8245,"minStay":2,"pricePerNight":656,"totalPrice":4027,"rating":2},
{"title":"Twitterbridge","sleeps":13,"bedRooms":3,"bathRooms":4,"halfBaths":3,"area":9777,"minStay":5,"pricePerNight":502,"totalPrice":7486,"rating":5},
{"title":"Pixoboo","sleeps":13,"bedRooms":4,"bathRooms":3,"halfBaths":4,"area":9383,"minStay":5,"pricePerNight":184,"totalPrice":8090,"rating":5},
{"title":"Quamba","sleeps":8,"bedRooms":5,"bathRooms":3,"halfBaths":2,"area":8632,"minStay":5,"pricePerNight":187,"totalPrice":3802,"rating":1},
{"title":"Agivu","sleeps":20,"bedRooms":3,"bathRooms":2,"halfBaths":5,"area":7537,"minStay":5,"pricePerNight":227,"totalPrice":3719,"rating":3},
{"title":"Thoughtstorm","sleeps":13,"bedRooms":3,"bathRooms":3,"halfBaths":4,"area":8726,"minStay":2,"pricePerNight":376,"totalPrice":9770,"rating":3},
{"title":"Trilia","sleeps":20,"bedRooms":4,"bathRooms":2,"halfBaths":1,"area":9057,"minStay":2,"pricePerNight":446,"totalPrice":5379,"rating":3},
{"title":"Blogtags","sleeps":10,"bedRooms":4,"bathRooms":3,"halfBaths":3,"area":8068,"minStay":4,"pricePerNight":281,"totalPrice":7549,"rating":1},
{"title":"Kwilith","sleeps":10,"bedRooms":1,"bathRooms":3,"halfBaths":5,"area":9868,"minStay":5,"pricePerNight":436,"totalPrice":9022,"rating":2},
{"title":"Riffwire","sleeps":4,"bedRooms":4,"bathRooms":4,"halfBaths":4,"area":7722,"minStay":5,"pricePerNight":661,"totalPrice":3927,"rating":5},
{"title":"Devpoint","sleeps":3,"bedRooms":4,"bathRooms":1,"halfBaths":3,"area":9114,"minStay":3,"pricePerNight":614,"totalPrice":7925,"rating":5},
{"title":"Flashspan","sleeps":7,"bedRooms":4,"bathRooms":3,"halfBaths":2,"area":8840,"minStay":4,"pricePerNight":605,"totalPrice":6130,"rating":3},
{"title":"Jetpulse","sleeps":11,"bedRooms":4,"bathRooms":3,"halfBaths":2,"area":8375,"minStay":3,"pricePerNight":185,"totalPrice":5715,"rating":3},
{"title":"Fadeo","sleeps":14,"bedRooms":3,"bathRooms":2,"halfBaths":1,"area":7705,"minStay":3,"pricePerNight":348,"totalPrice":9644,"rating":5},
{"title":"Yadel","sleeps":1,"bedRooms":1,"bathRooms":2,"halfBaths":5,"area":9004,"minStay":4,"pricePerNight":280,"totalPrice":8364,"rating":4},
{"title":"Ainyx","sleeps":4,"bedRooms":1,"bathRooms":2,"halfBaths":4,"area":7804,"minStay":3,"pricePerNight":249,"totalPrice":4326,"rating":4},
{"title":"Fivespan","sleeps":7,"bedRooms":4,"bathRooms":3,"halfBaths":4,"area":9554,"minStay":2,"pricePerNight":546,"totalPrice":9884,"rating":5},
{"title":"Oozz","sleeps":19,"bedRooms":1,"bathRooms":3,"halfBaths":1,"area":8002,"minStay":3,"pricePerNight":414,"totalPrice":6138,"rating":1},
{"title":"Minyx","sleeps":2,"bedRooms":4,"bathRooms":3,"halfBaths":2,"area":9500,"minStay":3,"pricePerNight":582,"totalPrice":3712,"rating":4},
{"title":"Dablist","sleeps":12,"bedRooms":2,"bathRooms":4,"halfBaths":2,"area":8964,"minStay":5,"pricePerNight":515,"totalPrice":9688,"rating":3},
{"title":"Realcube","sleeps":17,"bedRooms":1,"bathRooms":4,"halfBaths":3,"area":9359,"minStay":2,"pricePerNight":570,"totalPrice":8654,"rating":4},
{"title":"Jetwire","sleeps":15,"bedRooms":5,"bathRooms":2,"halfBaths":3,"area":9522,"minStay":5,"pricePerNight":364,"totalPrice":4874,"rating":1},
{"title":"Quire","sleeps":10,"bedRooms":3,"bathRooms":4,"halfBaths":4,"area":9855,"minStay":2,"pricePerNight":113,"totalPrice":8928,"rating":1},
{"title":"Demimbu","sleeps":3,"bedRooms":1,"bathRooms":1,"halfBaths":4,"area":9185,"minStay":5,"pricePerNight":524,"totalPrice":7166,"rating":2},
{"title":"Skibox","sleeps":10,"bedRooms":5,"bathRooms":2,"halfBaths":4,"area":7636,"minStay":5,"pricePerNight":227,"totalPrice":4669,"rating":4},
{"title":"Thoughtmix","sleeps":12,"bedRooms":4,"bathRooms":4,"halfBaths":5,"area":9778,"minStay":2,"pricePerNight":582,"totalPrice":3952,"rating":5},
{"title":"Oyope","sleeps":19,"bedRooms":2,"bathRooms":1,"halfBaths":1,"area":9851,"minStay":5,"pricePerNight":504,"totalPrice":3998,"rating":1},
{"title":"Quimm","sleeps":16,"bedRooms":1,"bathRooms":1,"halfBaths":5,"area":9115,"minStay":4,"pricePerNight":271,"totalPrice":9437,"rating":4},
{"title":"Skidoo","sleeps":3,"bedRooms":5,"bathRooms":2,"halfBaths":1,"area":8654,"minStay":3,"pricePerNight":131,"totalPrice":3182,"rating":1},
{"title":"Centidel","sleeps":7,"bedRooms":3,"bathRooms":1,"halfBaths":5,"area":7935,"minStay":3,"pricePerNight":595,"totalPrice":8629,"rating":3},
{"title":"Layo","sleeps":19,"bedRooms":1,"bathRooms":4,"halfBaths":3,"area":9342,"minStay":3,"pricePerNight":125,"totalPrice":6440,"rating":3},
{"title":"Rhynoodle","sleeps":16,"bedRooms":3,"bathRooms":2,"halfBaths":4,"area":8393,"minStay":3,"pricePerNight":106,"totalPrice":9899,"rating":1},
{"title":"Bluejam","sleeps":1,"bedRooms":3,"bathRooms":4,"halfBaths":1,"area":8031,"minStay":5,"pricePerNight":427,"totalPrice":3280,"rating":3},
{"title":"Oozz","sleeps":9,"bedRooms":2,"bathRooms":2,"halfBaths":2,"area":9100,"minStay":2,"pricePerNight":365,"totalPrice":9981,"rating":3},
{"title":"Skimia","sleeps":11,"bedRooms":3,"bathRooms":1,"halfBaths":1,"area":9160,"minStay":5,"pricePerNight":268,"totalPrice":3986,"rating":2},
{"title":"Leenti","sleeps":5,"bedRooms":4,"bathRooms":4,"halfBaths":4,"area":7857,"minStay":2,"pricePerNight":383,"totalPrice":8268,"rating":5},
{"title":"Flipbug","sleeps":9,"bedRooms":2,"bathRooms":3,"halfBaths":3,"area":8622,"minStay":5,"pricePerNight":349,"totalPrice":9433,"rating":3},
{"title":"Yakijo","sleeps":16,"bedRooms":1,"bathRooms":4,"halfBaths":5,"area":7590,"minStay":3,"pricePerNight":256,"totalPrice":4209,"rating":2},
{"title":"Trilia","sleeps":13,"bedRooms":4,"bathRooms":4,"halfBaths":3,"area":9719,"minStay":2,"pricePerNight":337,"totalPrice":3435,"rating":5},
{"title":"Edgeblab","sleeps":19,"bedRooms":5,"bathRooms":2,"halfBaths":1,"area":9835,"minStay":4,"pricePerNight":679,"totalPrice":3241,"rating":5},
{"title":"Meezzy","sleeps":19,"bedRooms":3,"bathRooms":4,"halfBaths":2,"area":8694,"minStay":4,"pricePerNight":692,"totalPrice":9299,"rating":5},
{"title":"Tekfly","sleeps":20,"bedRooms":3,"bathRooms":1,"halfBaths":5,"area":9879,"minStay":5,"pricePerNight":238,"totalPrice":7356,"rating":4},
{"title":"Youbridge","sleeps":15,"bedRooms":5,"bathRooms":2,"halfBaths":2,"area":9787,"minStay":5,"pricePerNight":284,"totalPrice":7928,"rating":5},
{"title":"Skiptube","sleeps":3,"bedRooms":1,"bathRooms":1,"halfBaths":4,"area":9524,"minStay":3,"pricePerNight":322,"totalPrice":8847,"rating":2},
{"title":"Quatz","sleeps":3,"bedRooms":1,"bathRooms":4,"halfBaths":4,"area":8369,"minStay":2,"pricePerNight":307,"totalPrice":9313,"rating":3},
{"title":"Dynazzy","sleeps":7,"bedRooms":3,"bathRooms":4,"halfBaths":4,"area":9585,"minStay":2,"pricePerNight":270,"totalPrice":4767,"rating":2},
{"title":"Eimbee","sleeps":13,"bedRooms":5,"bathRooms":2,"halfBaths":2,"area":7971,"minStay":4,"pricePerNight":545,"totalPrice":5126,"rating":5},
{"title":"Topicstorm","sleeps":10,"bedRooms":4,"bathRooms":2,"halfBaths":4,"area":9916,"minStay":3,"pricePerNight":614,"totalPrice":3481,"rating":5},
{"title":"Ntags","sleeps":2,"bedRooms":3,"bathRooms":2,"halfBaths":5,"area":9523,"minStay":3,"pricePerNight":157,"totalPrice":8399,"rating":2},
{"title":"Browseblab","sleeps":3,"bedRooms":4,"bathRooms":4,"halfBaths":5,"area":8289,"minStay":4,"pricePerNight":154,"totalPrice":6137,"rating":3},
{"title":"Thoughtstorm","sleeps":14,"bedRooms":3,"bathRooms":4,"halfBaths":4,"area":8656,"minStay":5,"pricePerNight":194,"totalPrice":7683,"rating":1},
{"title":"Gigabox","sleeps":20,"bedRooms":3,"bathRooms":2,"halfBaths":1,"area":9085,"minStay":5,"pricePerNight":595,"totalPrice":6513,"rating":5},
{"title":"Zoomcast","sleeps":5,"bedRooms":2,"bathRooms":2,"halfBaths":5,"area":8677,"minStay":3,"pricePerNight":424,"totalPrice":4917,"rating":2},
{"title":"Camido","sleeps":12,"bedRooms":1,"bathRooms":4,"halfBaths":2,"area":9222,"minStay":3,"pricePerNight":186,"totalPrice":3259,"rating":3},
{"title":"Jabbertype","sleeps":2,"bedRooms":2,"bathRooms":4,"halfBaths":4,"area":8730,"minStay":2,"pricePerNight":312,"totalPrice":4024,"rating":1},
{"title":"Vidoo","sleeps":7,"bedRooms":1,"bathRooms":4,"halfBaths":4,"area":7523,"minStay":3,"pricePerNight":268,"totalPrice":8033,"rating":2},
{"title":"Demivee","sleeps":6,"bedRooms":4,"bathRooms":2,"halfBaths":1,"area":9544,"minStay":5,"pricePerNight":482,"totalPrice":8938,"rating":2},
{"title":"Zoomdog","sleeps":8,"bedRooms":2,"bathRooms":2,"halfBaths":2,"area":9981,"minStay":4,"pricePerNight":490,"totalPrice":3237,"rating":4},
{"title":"Jabbercube","sleeps":4,"bedRooms":2,"bathRooms":4,"halfBaths":1,"area":9439,"minStay":5,"pricePerNight":272,"totalPrice":4855,"rating":1},
{"title":"Kwimbee","sleeps":6,"bedRooms":3,"bathRooms":4,"halfBaths":1,"area":9848,"minStay":5,"pricePerNight":597,"totalPrice":3767,"rating":3},
{"title":"Wikido","sleeps":9,"bedRooms":2,"bathRooms":2,"halfBaths":4,"area":8145,"minStay":2,"pricePerNight":180,"totalPrice":9199,"rating":4},
{"title":"Blogpad","sleeps":20,"bedRooms":3,"bathRooms":4,"halfBaths":4,"area":7598,"minStay":2,"pricePerNight":583,"totalPrice":8265,"rating":1},
{"title":"Ntag","sleeps":7,"bedRooms":4,"bathRooms":4,"halfBaths":4,"area":7525,"minStay":4,"pricePerNight":283,"totalPrice":8491,"rating":2},
{"title":"Fiveclub","sleeps":1,"bedRooms":2,"bathRooms":4,"halfBaths":4,"area":8823,"minStay":3,"pricePerNight":333,"totalPrice":9905,"rating":4},
{"title":"Nlounge","sleeps":11,"bedRooms":1,"bathRooms":4,"halfBaths":5,"area":9701,"minStay":2,"pricePerNight":413,"totalPrice":3956,"rating":3},
{"title":"Shufflester","sleeps":17,"bedRooms":5,"bathRooms":2,"halfBaths":5,"area":7534,"minStay":5,"pricePerNight":306,"totalPrice":5923,"rating":3},
{"title":"Dabshots","sleeps":16,"bedRooms":1,"bathRooms":2,"halfBaths":3,"area":8843,"minStay":3,"pricePerNight":414,"totalPrice":7691,"rating":4},
{"title":"Realblab","sleeps":6,"bedRooms":3,"bathRooms":2,"halfBaths":3,"area":9313,"minStay":5,"pricePerNight":319,"totalPrice":3611,"rating":4},
{"title":"Tazzy","sleeps":15,"bedRooms":5,"bathRooms":2,"halfBaths":1,"area":8950,"minStay":2,"pricePerNight":639,"totalPrice":5435,"rating":2},
{"title":"Flashpoint","sleeps":11,"bedRooms":1,"bathRooms":2,"halfBaths":4,"area":7714,"minStay":2,"pricePerNight":430,"totalPrice":3284,"rating":1},
{"title":"Jabbersphere","sleeps":5,"bedRooms":3,"bathRooms":4,"halfBaths":5,"area":8550,"minStay":5,"pricePerNight":684,"totalPrice":5346,"rating":4},
{"title":"Linklinks","sleeps":4,"bedRooms":3,"bathRooms":3,"halfBaths":1,"area":8269,"minStay":2,"pricePerNight":576,"totalPrice":7394,"rating":3},
{"title":"Realmix","sleeps":2,"bedRooms":2,"bathRooms":2,"halfBaths":3,"area":9874,"minStay":4,"pricePerNight":443,"totalPrice":9235,"rating":5},
{"title":"Skivee","sleeps":12,"bedRooms":1,"bathRooms":4,"halfBaths":4,"area":9344,"minStay":4,"pricePerNight":203,"totalPrice":7650,"rating":5},
{"title":"Linkbuzz","sleeps":8,"bedRooms":1,"bathRooms":1,"halfBaths":5,"area":8654,"minStay":5,"pricePerNight":359,"totalPrice":8331,"rating":1},
{"title":"Miboo","sleeps":7,"bedRooms":2,"bathRooms":2,"halfBaths":4,"area":9414,"minStay":5,"pricePerNight":337,"totalPrice":5207,"rating":5},
{"title":"Babblestorm","sleeps":12,"bedRooms":2,"bathRooms":1,"halfBaths":5,"area":9553,"minStay":4,"pricePerNight":326,"totalPrice":8815,"rating":5},
{"title":"Twitterbeat","sleeps":2,"bedRooms":2,"bathRooms":2,"halfBaths":5,"area":9609,"minStay":2,"pricePerNight":206,"totalPrice":7191,"rating":5},
{"title":"Quimm","sleeps":14,"bedRooms":1,"bathRooms":2,"halfBaths":2,"area":7962,"minStay":4,"pricePerNight":360,"totalPrice":7631,"rating":1},
{"title":"Eayo","sleeps":17,"bedRooms":2,"bathRooms":2,"halfBaths":4,"area":9221,"minStay":3,"pricePerNight":401,"totalPrice":5974,"rating":2},
{"title":"Vitz","sleeps":9,"bedRooms":4,"bathRooms":1,"halfBaths":2,"area":9156,"minStay":5,"pricePerNight":663,"totalPrice":7141,"rating":2},
{"title":"Tanoodle","sleeps":1,"bedRooms":3,"bathRooms":3,"halfBaths":5,"area":8945,"minStay":2,"pricePerNight":169,"totalPrice":9136,"rating":2},
{"title":"Brightdog","sleeps":12,"bedRooms":3,"bathRooms":1,"halfBaths":3,"area":8783,"minStay":3,"pricePerNight":469,"totalPrice":6278,"rating":5},
{"title":"Mita","sleeps":16,"bedRooms":5,"bathRooms":4,"halfBaths":4,"area":9951,"minStay":5,"pricePerNight":281,"totalPrice":7555,"rating":4},
{"title":"Dablist","sleeps":8,"bedRooms":1,"bathRooms":1,"halfBaths":5,"area":7967,"minStay":5,"pricePerNight":478,"totalPrice":9366,"rating":3},
{"title":"Mydo","sleeps":12,"bedRooms":4,"bathRooms":4,"halfBaths":5,"area":8427,"minStay":4,"pricePerNight":640,"totalPrice":3606,"rating":4},
{"title":"Oyoyo","sleeps":9,"bedRooms":1,"bathRooms":2,"halfBaths":4,"area":7707,"minStay":4,"pricePerNight":498,"totalPrice":7564,"rating":1},
{"title":"Feedmix","sleeps":17,"bedRooms":3,"bathRooms":1,"halfBaths":2,"area":8870,"minStay":4,"pricePerNight":630,"totalPrice":7166,"rating":2},
{"title":"Zoomzone","sleeps":4,"bedRooms":5,"bathRooms":4,"halfBaths":4,"area":9167,"minStay":4,"pricePerNight":516,"totalPrice":9938,"rating":4},
{"title":"Talane","sleeps":14,"bedRooms":5,"bathRooms":1,"halfBaths":3,"area":9241,"minStay":5,"pricePerNight":495,"totalPrice":3751,"rating":5},
{"title":"Yadel","sleeps":1,"bedRooms":4,"bathRooms":4,"halfBaths":1,"area":9695,"minStay":3,"pricePerNight":162,"totalPrice":6346,"rating":3},
{"title":"Zoomlounge","sleeps":18,"bedRooms":5,"bathRooms":2,"halfBaths":1,"area":7656,"minStay":4,"pricePerNight":130,"totalPrice":6003,"rating":1},
{"title":"Topicshots","sleeps":13,"bedRooms":5,"bathRooms":4,"halfBaths":4,"area":8423,"minStay":3,"pricePerNight":132,"totalPrice":6482,"rating":1},
{"title":"Digitube","sleeps":12,"bedRooms":2,"bathRooms":2,"halfBaths":4,"area":9224,"minStay":2,"pricePerNight":239,"totalPrice":6288,"rating":4},
{"title":"Podcat","sleeps":9,"bedRooms":3,"bathRooms":3,"halfBaths":3,"area":8229,"minStay":3,"pricePerNight":193,"totalPrice":8176,"rating":3},
{"title":"Thoughtstorm","sleeps":4,"bedRooms":4,"bathRooms":4,"halfBaths":2,"area":8634,"minStay":3,"pricePerNight":323,"totalPrice":3157,"rating":5},
{"title":"Trudeo","sleeps":15,"bedRooms":4,"bathRooms":1,"halfBaths":5,"area":8377,"minStay":2,"pricePerNight":575,"totalPrice":5766,"rating":5},
{"title":"Jaloo","sleeps":17,"bedRooms":2,"bathRooms":3,"halfBaths":5,"area":9462,"minStay":3,"pricePerNight":106,"totalPrice":3381,"rating":2},
{"title":"Wikido","sleeps":1,"bedRooms":4,"bathRooms":1,"halfBaths":4,"area":7810,"minStay":4,"pricePerNight":529,"totalPrice":8411,"rating":3},
{"title":"Tazz","sleeps":8,"bedRooms":1,"bathRooms":2,"halfBaths":5,"area":9347,"minStay":3,"pricePerNight":310,"totalPrice":7281,"rating":2},
{"title":"Kazio","sleeps":9,"bedRooms":4,"bathRooms":4,"halfBaths":4,"area":9291,"minStay":4,"pricePerNight":319,"totalPrice":7370,"rating":2},
{"title":"Mybuzz","sleeps":12,"bedRooms":3,"bathRooms":1,"halfBaths":2,"area":7670,"minStay":4,"pricePerNight":365,"totalPrice":4089,"rating":2},
{"title":"Jaxworks","sleeps":4,"bedRooms":1,"bathRooms":2,"halfBaths":5,"area":7572,"minStay":5,"pricePerNight":495,"totalPrice":8850,"rating":4},
{"title":"Devcast","sleeps":17,"bedRooms":3,"bathRooms":3,"halfBaths":4,"area":7583,"minStay":4,"pricePerNight":581,"totalPrice":7420,"rating":2},
{"title":"Blogpad","sleeps":8,"bedRooms":5,"bathRooms":1,"halfBaths":5,"area":9857,"minStay":4,"pricePerNight":441,"totalPrice":4573,"rating":3},
{"title":"Zoomdog","sleeps":8,"bedRooms":4,"bathRooms":4,"halfBaths":1,"area":8275,"minStay":2,"pricePerNight":505,"totalPrice":9888,"rating":2},
{"title":"Blogspan","sleeps":1,"bedRooms":3,"bathRooms":2,"halfBaths":1,"area":9914,"minStay":4,"pricePerNight":242,"totalPrice":5034,"rating":5},
{"title":"Centidel","sleeps":1,"bedRooms":3,"bathRooms":1,"halfBaths":3,"area":7923,"minStay":3,"pricePerNight":314,"totalPrice":4239,"rating":5},
{"title":"Miboo","sleeps":9,"bedRooms":4,"bathRooms":4,"halfBaths":4,"area":8510,"minStay":2,"pricePerNight":250,"totalPrice":8868,"rating":1},
{"title":"Oyoloo","sleeps":19,"bedRooms":2,"bathRooms":2,"halfBaths":2,"area":8625,"minStay":3,"pricePerNight":555,"totalPrice":8738,"rating":3},
{"title":"Dabjam","sleeps":16,"bedRooms":1,"bathRooms":2,"halfBaths":5,"area":9839,"minStay":2,"pricePerNight":622,"totalPrice":8668,"rating":3},
{"title":"Reallinks","sleeps":19,"bedRooms":4,"bathRooms":4,"halfBaths":3,"area":8460,"minStay":3,"pricePerNight":330,"totalPrice":3025,"rating":4},
{"title":"Avamm","sleeps":13,"bedRooms":3,"bathRooms":3,"halfBaths":1,"area":8955,"minStay":4,"pricePerNight":495,"totalPrice":3288,"rating":4},
{"title":"Skinix","sleeps":10,"bedRooms":1,"bathRooms":4,"halfBaths":2,"area":8950,"minStay":5,"pricePerNight":300,"totalPrice":9186,"rating":4},
{"title":"Eadel","sleeps":9,"bedRooms":5,"bathRooms":2,"halfBaths":2,"area":9612,"minStay":5,"pricePerNight":303,"totalPrice":4462,"rating":4},
{"title":"Voonix","sleeps":10,"bedRooms":1,"bathRooms":2,"halfBaths":3,"area":7803,"minStay":4,"pricePerNight":263,"totalPrice":6263,"rating":3},
{"title":"Pixonyx","sleeps":17,"bedRooms":4,"bathRooms":1,"halfBaths":1,"area":7751,"minStay":4,"pricePerNight":338,"totalPrice":7222,"rating":5},
{"title":"Gigaclub","sleeps":7,"bedRooms":1,"bathRooms":4,"halfBaths":3,"area":7689,"minStay":4,"pricePerNight":563,"totalPrice":6456,"rating":4},
{"title":"Twinder","sleeps":8,"bedRooms":4,"bathRooms":2,"halfBaths":2,"area":8015,"minStay":3,"pricePerNight":613,"totalPrice":7690,"rating":4},
{"title":"Oyoyo","sleeps":16,"bedRooms":1,"bathRooms":3,"halfBaths":4,"area":7964,"minStay":2,"pricePerNight":104,"totalPrice":5994,"rating":2},
{"title":"Buzzshare","sleeps":11,"bedRooms":5,"bathRooms":4,"halfBaths":2,"area":9976,"minStay":5,"pricePerNight":109,"totalPrice":4177,"rating":4},
{"title":"Bluejam","sleeps":2,"bedRooms":5,"bathRooms":3,"halfBaths":4,"area":9314,"minStay":3,"pricePerNight":608,"totalPrice":7755,"rating":1},
{"title":"Plambee","sleeps":14,"bedRooms":4,"bathRooms":1,"halfBaths":4,"area":7994,"minStay":3,"pricePerNight":126,"totalPrice":7958,"rating":3},
{"title":"Kwideo","sleeps":10,"bedRooms":5,"bathRooms":4,"halfBaths":1,"area":8132,"minStay":5,"pricePerNight":359,"totalPrice":8931,"rating":1},
{"title":"Fanoodle","sleeps":5,"bedRooms":4,"bathRooms":1,"halfBaths":5,"area":9095,"minStay":3,"pricePerNight":332,"totalPrice":7057,"rating":1},
{"title":"Quatz","sleeps":1,"bedRooms":3,"bathRooms":1,"halfBaths":4,"area":9682,"minStay":2,"pricePerNight":154,"totalPrice":4631,"rating":4},
{"title":"Twitterlist","sleeps":17,"bedRooms":2,"bathRooms":2,"halfBaths":1,"area":8162,"minStay":5,"pricePerNight":489,"totalPrice":9032,"rating":5},
{"title":"Jabberstorm","sleeps":6,"bedRooms":2,"bathRooms":4,"halfBaths":3,"area":7627,"minStay":5,"pricePerNight":645,"totalPrice":9522,"rating":1},
{"title":"Tagfeed","sleeps":4,"bedRooms":5,"bathRooms":2,"halfBaths":3,"area":8384,"minStay":5,"pricePerNight":656,"totalPrice":6162,"rating":5},
{"title":"Browsebug","sleeps":5,"bedRooms":3,"bathRooms":2,"halfBaths":4,"area":9781,"minStay":5,"pricePerNight":266,"totalPrice":9688,"rating":2},
{"title":"Dynabox","sleeps":12,"bedRooms":3,"bathRooms":3,"halfBaths":4,"area":9888,"minStay":5,"pricePerNight":440,"totalPrice":3749,"rating":1},
{"title":"Mita","sleeps":18,"bedRooms":1,"bathRooms":3,"halfBaths":1,"area":9827,"minStay":5,"pricePerNight":538,"totalPrice":5184,"rating":5},
{"title":"Skiptube","sleeps":16,"bedRooms":5,"bathRooms":3,"halfBaths":1,"area":9696,"minStay":3,"pricePerNight":488,"totalPrice":4183,"rating":1},
{"title":"Jabbertype","sleeps":8,"bedRooms":2,"bathRooms":1,"halfBaths":4,"area":9712,"minStay":5,"pricePerNight":129,"totalPrice":7129,"rating":5},
{"title":"Realfire","sleeps":13,"bedRooms":1,"bathRooms":2,"halfBaths":1,"area":7907,"minStay":2,"pricePerNight":216,"totalPrice":9545,"rating":3},
{"title":"Centimia","sleeps":6,"bedRooms":2,"bathRooms":1,"halfBaths":5,"area":9478,"minStay":5,"pricePerNight":369,"totalPrice":5256,"rating":4},
{"title":"Skipfire","sleeps":20,"bedRooms":5,"bathRooms":1,"halfBaths":4,"area":8290,"minStay":4,"pricePerNight":521,"totalPrice":9207,"rating":3},
{"title":"Midel","sleeps":8,"bedRooms":4,"bathRooms":1,"halfBaths":4,"area":8915,"minStay":5,"pricePerNight":363,"totalPrice":7843,"rating":3},
{"title":"Gigaclub","sleeps":14,"bedRooms":3,"bathRooms":1,"halfBaths":4,"area":9105,"minStay":4,"pricePerNight":425,"totalPrice":9504,"rating":5},
{"title":"Chatterpoint","sleeps":1,"bedRooms":5,"bathRooms":2,"halfBaths":4,"area":7920,"minStay":4,"pricePerNight":350,"totalPrice":4917,"rating":3},
{"title":"Skidoo","sleeps":12,"bedRooms":4,"bathRooms":3,"halfBaths":1,"area":7776,"minStay":5,"pricePerNight":345,"totalPrice":8059,"rating":5},
{"title":"Realfire","sleeps":7,"bedRooms":2,"bathRooms":4,"halfBaths":4,"area":8300,"minStay":2,"pricePerNight":466,"totalPrice":9213,"rating":5},
{"title":"Realbuzz","sleeps":4,"bedRooms":5,"bathRooms":4,"halfBaths":1,"area":7615,"minStay":2,"pricePerNight":684,"totalPrice":6151,"rating":1},
{"title":"Livefish","sleeps":3,"bedRooms":4,"bathRooms":1,"halfBaths":3,"area":7840,"minStay":3,"pricePerNight":228,"totalPrice":5118,"rating":2},
{"title":"Youtags","sleeps":18,"bedRooms":4,"bathRooms":4,"halfBaths":3,"area":9633,"minStay":3,"pricePerNight":699,"totalPrice":4694,"rating":1},
{"title":"Jetpulse","sleeps":3,"bedRooms":3,"bathRooms":1,"halfBaths":3,"area":8152,"minStay":5,"pricePerNight":448,"totalPrice":9427,"rating":2},
{"title":"Ntags","sleeps":13,"bedRooms":4,"bathRooms":3,"halfBaths":5,"area":9102,"minStay":4,"pricePerNight":393,"totalPrice":6507,"rating":1},
{"title":"Zazio","sleeps":15,"bedRooms":5,"bathRooms":3,"halfBaths":1,"area":7671,"minStay":3,"pricePerNight":356,"totalPrice":7581,"rating":4},
{"title":"Skyba","sleeps":12,"bedRooms":2,"bathRooms":2,"halfBaths":3,"area":7975,"minStay":5,"pricePerNight":551,"totalPrice":9392,"rating":3},
{"title":"Voonix","sleeps":15,"bedRooms":5,"bathRooms":1,"halfBaths":2,"area":9910,"minStay":4,"pricePerNight":118,"totalPrice":8081,"rating":1},
{"title":"Jayo","sleeps":16,"bedRooms":2,"bathRooms":1,"halfBaths":3,"area":9997,"minStay":3,"pricePerNight":640,"totalPrice":5255,"rating":3},
{"title":"Dablist","sleeps":2,"bedRooms":1,"bathRooms":3,"halfBaths":1,"area":7774,"minStay":2,"pricePerNight":384,"totalPrice":9692,"rating":2},
{"title":"Kwideo","sleeps":3,"bedRooms":2,"bathRooms":1,"halfBaths":5,"area":8931,"minStay":2,"pricePerNight":522,"totalPrice":7579,"rating":4},
{"title":"Digitube","sleeps":9,"bedRooms":3,"bathRooms":2,"halfBaths":5,"area":8656,"minStay":5,"pricePerNight":675,"totalPrice":4386,"rating":1},
{"title":"Teklist","sleeps":2,"bedRooms":3,"bathRooms":3,"halfBaths":3,"area":8819,"minStay":4,"pricePerNight":359,"totalPrice":7530,"rating":3},
{"title":"Eare","sleeps":9,"bedRooms":1,"bathRooms":3,"halfBaths":5,"area":9736,"minStay":5,"pricePerNight":644,"totalPrice":9847,"rating":1},
{"title":"Riffwire","sleeps":15,"bedRooms":1,"bathRooms":1,"halfBaths":1,"area":9047,"minStay":3,"pricePerNight":427,"totalPrice":6009,"rating":5},
{"title":"Jaxworks","sleeps":7,"bedRooms":1,"bathRooms":1,"halfBaths":1,"area":9181,"minStay":3,"pricePerNight":330,"totalPrice":5281,"rating":1},
{"title":"Edgeblab","sleeps":13,"bedRooms":3,"bathRooms":4,"halfBaths":5,"area":8608,"minStay":5,"pricePerNight":690,"totalPrice":3357,"rating":4},
{"title":"Realpoint","sleeps":20,"bedRooms":4,"bathRooms":4,"halfBaths":1,"area":8077,"minStay":2,"pricePerNight":564,"totalPrice":6496,"rating":3},
{"title":"Centimia","sleeps":5,"bedRooms":5,"bathRooms":4,"halfBaths":4,"area":7712,"minStay":5,"pricePerNight":509,"totalPrice":6684,"rating":2},
{"title":"Feedmix","sleeps":2,"bedRooms":2,"bathRooms":4,"halfBaths":4,"area":7680,"minStay":5,"pricePerNight":445,"totalPrice":7282,"rating":4},
{"title":"Kayveo","sleeps":4,"bedRooms":2,"bathRooms":3,"halfBaths":2,"area":9374,"minStay":5,"pricePerNight":442,"totalPrice":5443,"rating":1},
{"title":"Livetube","sleeps":4,"bedRooms":3,"bathRooms":4,"halfBaths":4,"area":9736,"minStay":5,"pricePerNight":428,"totalPrice":3452,"rating":2},
{"title":"Yozio","sleeps":18,"bedRooms":2,"bathRooms":2,"halfBaths":3,"area":7842,"minStay":2,"pricePerNight":662,"totalPrice":5558,"rating":4},
{"title":"Jamia","sleeps":9,"bedRooms":1,"bathRooms":2,"halfBaths":3,"area":9268,"minStay":2,"pricePerNight":408,"totalPrice":4411,"rating":5},
{"title":"Thoughtworks","sleeps":9,"bedRooms":5,"bathRooms":3,"halfBaths":2,"area":8137,"minStay":5,"pricePerNight":233,"totalPrice":8623,"rating":3},
{"title":"Wikizz","sleeps":15,"bedRooms":1,"bathRooms":1,"halfBaths":5,"area":7594,"minStay":3,"pricePerNight":301,"totalPrice":4210,"rating":2},
{"title":"Leexo","sleeps":3,"bedRooms":2,"bathRooms":2,"halfBaths":3,"area":7529,"minStay":5,"pricePerNight":110,"totalPrice":6524,"rating":4},
{"title":"Voonder","sleeps":20,"bedRooms":3,"bathRooms":3,"halfBaths":4,"area":8816,"minStay":5,"pricePerNight":417,"totalPrice":3605,"rating":3},
{"title":"Dabfeed","sleeps":16,"bedRooms":4,"bathRooms":3,"halfBaths":2,"area":8558,"minStay":2,"pricePerNight":510,"totalPrice":4153,"rating":2},
{"title":"Tagtune","sleeps":5,"bedRooms":4,"bathRooms":3,"halfBaths":1,"area":9727,"minStay":5,"pricePerNight":339,"totalPrice":5484,"rating":5},
{"title":"Shufflebeat","sleeps":2,"bedRooms":4,"bathRooms":1,"halfBaths":2,"area":8830,"minStay":3,"pricePerNight":650,"totalPrice":3709,"rating":3},
{"title":"Blogspan","sleeps":10,"bedRooms":1,"bathRooms":2,"halfBaths":5,"area":9140,"minStay":2,"pricePerNight":201,"totalPrice":5101,"rating":4},
{"title":"Kamba","sleeps":2,"bedRooms":3,"bathRooms":2,"halfBaths":5,"area":7997,"minStay":5,"pricePerNight":268,"totalPrice":4799,"rating":2},
{"title":"Feedspan","sleeps":8,"bedRooms":3,"bathRooms":1,"halfBaths":5,"area":8709,"minStay":2,"pricePerNight":687,"totalPrice":9001,"rating":3},
{"title":"Miboo","sleeps":2,"bedRooms":3,"bathRooms":4,"halfBaths":2,"area":8692,"minStay":5,"pricePerNight":586,"totalPrice":7493,"rating":5},
{"title":"Oba","sleeps":13,"bedRooms":5,"bathRooms":4,"halfBaths":2,"area":9028,"minStay":2,"pricePerNight":260,"totalPrice":5684,"rating":1},
{"title":"Flashset","sleeps":10,"bedRooms":4,"bathRooms":3,"halfBaths":1,"area":8428,"minStay":5,"pricePerNight":219,"totalPrice":6543,"rating":2},
{"title":"Devpulse","sleeps":8,"bedRooms":1,"bathRooms":4,"halfBaths":2,"area":9354,"minStay":5,"pricePerNight":418,"totalPrice":5918,"rating":5},
{"title":"Tagopia","sleeps":20,"bedRooms":4,"bathRooms":3,"halfBaths":1,"area":8608,"minStay":4,"pricePerNight":683,"totalPrice":4194,"rating":1},
{"title":"Topiczoom","sleeps":16,"bedRooms":2,"bathRooms":1,"halfBaths":4,"area":8459,"minStay":5,"pricePerNight":314,"totalPrice":9420,"rating":3},
{"title":"Edgeclub","sleeps":13,"bedRooms":3,"bathRooms":3,"halfBaths":4,"area":7544,"minStay":3,"pricePerNight":683,"totalPrice":8139,"rating":3},
{"title":"Quatz","sleeps":19,"bedRooms":5,"bathRooms":3,"halfBaths":1,"area":9378,"minStay":4,"pricePerNight":447,"totalPrice":8338,"rating":1},
{"title":"Agimba","sleeps":14,"bedRooms":1,"bathRooms":2,"halfBaths":2,"area":7766,"minStay":4,"pricePerNight":221,"totalPrice":4096,"rating":5},
{"title":"Linktype","sleeps":11,"bedRooms":2,"bathRooms":3,"halfBaths":1,"area":9448,"minStay":4,"pricePerNight":154,"totalPrice":3267,"rating":5},
{"title":"Youbridge","sleeps":13,"bedRooms":1,"bathRooms":1,"halfBaths":2,"area":8115,"minStay":2,"pricePerNight":425,"totalPrice":9906,"rating":4},
{"title":"Avamba","sleeps":3,"bedRooms":3,"bathRooms":3,"halfBaths":3,"area":8723,"minStay":4,"pricePerNight":331,"totalPrice":3649,"rating":5},
{"title":"Thoughtmix","sleeps":13,"bedRooms":3,"bathRooms":1,"halfBaths":3,"area":9869,"minStay":2,"pricePerNight":348,"totalPrice":4844,"rating":1},
{"title":"Youtags","sleeps":16,"bedRooms":4,"bathRooms":4,"halfBaths":1,"area":9685,"minStay":2,"pricePerNight":144,"totalPrice":8835,"rating":5},
{"title":"Dablist","sleeps":15,"bedRooms":1,"bathRooms":2,"halfBaths":3,"area":8045,"minStay":4,"pricePerNight":540,"totalPrice":5879,"rating":2},
{"title":"Jaxspan","sleeps":9,"bedRooms":2,"bathRooms":1,"halfBaths":4,"area":9993,"minStay":3,"pricePerNight":156,"totalPrice":3748,"rating":4},
{"title":"Skyndu","sleeps":9,"bedRooms":5,"bathRooms":3,"halfBaths":5,"area":7680,"minStay":4,"pricePerNight":268,"totalPrice":9473,"rating":5},
{"title":"Eadel","sleeps":6,"bedRooms":5,"bathRooms":3,"halfBaths":2,"area":7724,"minStay":5,"pricePerNight":346,"totalPrice":6852,"rating":2},
{"title":"Trilia","sleeps":20,"bedRooms":3,"bathRooms":1,"halfBaths":2,"area":8169,"minStay":4,"pricePerNight":624,"totalPrice":5976,"rating":3},
{"title":"Gigazoom","sleeps":7,"bedRooms":5,"bathRooms":3,"halfBaths":2,"area":9716,"minStay":3,"pricePerNight":259,"totalPrice":5130,"rating":3},
{"title":"Feedfire","sleeps":16,"bedRooms":2,"bathRooms":3,"halfBaths":2,"area":9876,"minStay":4,"pricePerNight":263,"totalPrice":9776,"rating":4},
{"title":"Einti","sleeps":18,"bedRooms":2,"bathRooms":4,"halfBaths":5,"area":9746,"minStay":2,"pricePerNight":661,"totalPrice":7559,"rating":5},
{"title":"Edgeify","sleeps":15,"bedRooms":4,"bathRooms":1,"halfBaths":3,"area":9811,"minStay":3,"pricePerNight":357,"totalPrice":4338,"rating":2},
{"title":"Yabox","sleeps":2,"bedRooms":3,"bathRooms":3,"halfBaths":5,"area":9855,"minStay":3,"pricePerNight":330,"totalPrice":4107,"rating":4},
{"title":"Devbug","sleeps":9,"bedRooms":2,"bathRooms":3,"halfBaths":5,"area":8671,"minStay":5,"pricePerNight":588,"totalPrice":3780,"rating":1},
{"title":"Aimbo","sleeps":1,"bedRooms":4,"bathRooms":1,"halfBaths":3,"area":9080,"minStay":3,"pricePerNight":318,"totalPrice":8702,"rating":4},
{"title":"Meetz","sleeps":7,"bedRooms":3,"bathRooms":1,"halfBaths":3,"area":8857,"minStay":5,"pricePerNight":174,"totalPrice":6040,"rating":5},
{"title":"Skibox","sleeps":7,"bedRooms":3,"bathRooms":2,"halfBaths":4,"area":9422,"minStay":4,"pricePerNight":534,"totalPrice":5976,"rating":5},
{"title":"Shuffledrive","sleeps":1,"bedRooms":2,"bathRooms":1,"halfBaths":5,"area":8383,"minStay":4,"pricePerNight":592,"totalPrice":8644,"rating":1},
{"title":"Twinder","sleeps":13,"bedRooms":5,"bathRooms":3,"halfBaths":4,"area":7899,"minStay":2,"pricePerNight":550,"totalPrice":3936,"rating":3},
{"title":"Roombo","sleeps":2,"bedRooms":5,"bathRooms":3,"halfBaths":4,"area":7656,"minStay":2,"pricePerNight":323,"totalPrice":3070,"rating":3},
{"title":"Skipstorm","sleeps":10,"bedRooms":5,"bathRooms":4,"halfBaths":1,"area":8546,"minStay":2,"pricePerNight":226,"totalPrice":5942,"rating":1},
{"title":"Rhynoodle","sleeps":19,"bedRooms":1,"bathRooms":4,"halfBaths":4,"area":8237,"minStay":2,"pricePerNight":394,"totalPrice":3664,"rating":2},
{"title":"Roodel","sleeps":1,"bedRooms":3,"bathRooms":2,"halfBaths":2,"area":8624,"minStay":2,"pricePerNight":138,"totalPrice":4900,"rating":2},
{"title":"Mudo","sleeps":7,"bedRooms":5,"bathRooms":2,"halfBaths":3,"area":8781,"minStay":2,"pricePerNight":691,"totalPrice":8439,"rating":3},
{"title":"Quamba","sleeps":10,"bedRooms":4,"bathRooms":4,"halfBaths":1,"area":7880,"minStay":3,"pricePerNight":329,"totalPrice":3842,"rating":2},
{"title":"Innojam","sleeps":16,"bedRooms":1,"bathRooms":1,"halfBaths":4,"area":8483,"minStay":2,"pricePerNight":116,"totalPrice":4135,"rating":2},
{"title":"Twitterbeat","sleeps":9,"bedRooms":2,"bathRooms":1,"halfBaths":2,"area":9647,"minStay":5,"pricePerNight":476,"totalPrice":8716,"rating":5},
{"title":"Brainsphere","sleeps":3,"bedRooms":4,"bathRooms":2,"halfBaths":1,"area":8752,"minStay":5,"pricePerNight":284,"totalPrice":5295,"rating":2},
{"title":"Roombo","sleeps":12,"bedRooms":4,"bathRooms":2,"halfBaths":3,"area":8837,"minStay":3,"pricePerNight":119,"totalPrice":4940,"rating":5},
{"title":"Innojam","sleeps":11,"bedRooms":2,"bathRooms":1,"halfBaths":4,"area":8719,"minStay":3,"pricePerNight":162,"totalPrice":5563,"rating":1},
{"title":"Oyoba","sleeps":10,"bedRooms":1,"bathRooms":4,"halfBaths":4,"area":9207,"minStay":5,"pricePerNight":253,"totalPrice":8722,"rating":4},
{"title":"Fivespan","sleeps":20,"bedRooms":3,"bathRooms":4,"halfBaths":5,"area":7557,"minStay":2,"pricePerNight":588,"totalPrice":6459,"rating":3},
{"title":"Skyvu","sleeps":4,"bedRooms":5,"bathRooms":3,"halfBaths":4,"area":8065,"minStay":2,"pricePerNight":659,"totalPrice":7724,"rating":1},
{"title":"Thoughtsphere","sleeps":16,"bedRooms":2,"bathRooms":1,"halfBaths":1,"area":8019,"minStay":2,"pricePerNight":187,"totalPrice":3017,"rating":1},
{"title":"Kanoodle","sleeps":19,"bedRooms":3,"bathRooms":4,"halfBaths":4,"area":7926,"minStay":2,"pricePerNight":123,"totalPrice":6329,"rating":1},
{"title":"Feedfire","sleeps":19,"bedRooms":1,"bathRooms":2,"halfBaths":3,"area":9832,"minStay":5,"pricePerNight":236,"totalPrice":8806,"rating":1},
{"title":"Twinte","sleeps":16,"bedRooms":2,"bathRooms":2,"halfBaths":1,"area":9820,"minStay":4,"pricePerNight":415,"totalPrice":5610,"rating":4},
{"title":"Jabbersphere","sleeps":4,"bedRooms":5,"bathRooms":3,"halfBaths":5,"area":8121,"minStay":5,"pricePerNight":427,"totalPrice":3217,"rating":4},
{"title":"Wikivu","sleeps":17,"bedRooms":4,"bathRooms":1,"halfBaths":2,"area":7565,"minStay":2,"pricePerNight":557,"totalPrice":5697,"rating":4},
{"title":"Cogilith","sleeps":1,"bedRooms":5,"bathRooms":3,"halfBaths":2,"area":7669,"minStay":4,"pricePerNight":417,"totalPrice":8348,"rating":1},
{"title":"Bluejam","sleeps":19,"bedRooms":2,"bathRooms":4,"halfBaths":2,"area":9927,"minStay":5,"pricePerNight":596,"totalPrice":5104,"rating":5},
{"title":"Gigazoom","sleeps":19,"bedRooms":5,"bathRooms":2,"halfBaths":4,"area":9285,"minStay":4,"pricePerNight":389,"totalPrice":3428,"rating":4},
{"title":"Eayo","sleeps":14,"bedRooms":2,"bathRooms":4,"halfBaths":5,"area":9789,"minStay":4,"pricePerNight":608,"totalPrice":8141,"rating":3},
{"title":"Skynoodle","sleeps":2,"bedRooms":4,"bathRooms":2,"halfBaths":1,"area":9375,"minStay":3,"pricePerNight":329,"totalPrice":6329,"rating":4},
{"title":"Leexo","sleeps":4,"bedRooms":3,"bathRooms":1,"halfBaths":2,"area":7876,"minStay":3,"pricePerNight":258,"totalPrice":3696,"rating":1},
{"title":"Quimm","sleeps":16,"bedRooms":3,"bathRooms":3,"halfBaths":1,"area":7575,"minStay":3,"pricePerNight":175,"totalPrice":3796,"rating":2},
{"title":"Feedfish","sleeps":17,"bedRooms":2,"bathRooms":2,"halfBaths":3,"area":9628,"minStay":5,"pricePerNight":353,"totalPrice":4211,"rating":5},
{"title":"Twimm","sleeps":4,"bedRooms":3,"bathRooms":3,"halfBaths":3,"area":8635,"minStay":5,"pricePerNight":421,"totalPrice":5555,"rating":3},
{"title":"Meedoo","sleeps":17,"bedRooms":4,"bathRooms":3,"halfBaths":2,"area":8355,"minStay":2,"pricePerNight":377,"totalPrice":6061,"rating":1},
{"title":"Jaxworks","sleeps":20,"bedRooms":4,"bathRooms":2,"halfBaths":1,"area":9919,"minStay":3,"pricePerNight":653,"totalPrice":6646,"rating":1},
{"title":"Voonix","sleeps":1,"bedRooms":3,"bathRooms":1,"halfBaths":1,"area":8381,"minStay":3,"pricePerNight":285,"totalPrice":5307,"rating":2},
{"title":"Fivebridge","sleeps":7,"bedRooms":4,"bathRooms":3,"halfBaths":5,"area":8915,"minStay":3,"pricePerNight":608,"totalPrice":7906,"rating":1},
{"title":"Mudo","sleeps":14,"bedRooms":1,"bathRooms":2,"halfBaths":2,"area":9409,"minStay":3,"pricePerNight":235,"totalPrice":8166,"rating":2},
{"title":"Topiclounge","sleeps":16,"bedRooms":3,"bathRooms":2,"halfBaths":1,"area":8490,"minStay":4,"pricePerNight":126,"totalPrice":3990,"rating":4},
{"title":"Ainyx","sleeps":13,"bedRooms":5,"bathRooms":1,"halfBaths":4,"area":8603,"minStay":3,"pricePerNight":682,"totalPrice":6267,"rating":2},
{"title":"Photospace","sleeps":6,"bedRooms":4,"bathRooms":1,"halfBaths":4,"area":8963,"minStay":5,"pricePerNight":226,"totalPrice":9365,"rating":2},
{"title":"Mydo","sleeps":1,"bedRooms":2,"bathRooms":3,"halfBaths":1,"area":8627,"minStay":5,"pricePerNight":676,"totalPrice":5609,"rating":2},
{"title":"Browseblab","sleeps":2,"bedRooms":2,"bathRooms":3,"halfBaths":1,"area":7649,"minStay":4,"pricePerNight":520,"totalPrice":8261,"rating":1},
{"title":"Meedoo","sleeps":15,"bedRooms":5,"bathRooms":3,"halfBaths":5,"area":7967,"minStay":2,"pricePerNight":563,"totalPrice":6562,"rating":5},
{"title":"Meejo","sleeps":14,"bedRooms":5,"bathRooms":1,"halfBaths":3,"area":8598,"minStay":4,"pricePerNight":628,"totalPrice":9257,"rating":2},
{"title":"Twitterbridge","sleeps":7,"bedRooms":3,"bathRooms":4,"halfBaths":4,"area":8681,"minStay":4,"pricePerNight":543,"totalPrice":8086,"rating":1},
{"title":"Jatri","sleeps":13,"bedRooms":1,"bathRooms":4,"halfBaths":1,"area":9230,"minStay":5,"pricePerNight":327,"totalPrice":5561,"rating":1},
{"title":"Twitterworks","sleeps":12,"bedRooms":2,"bathRooms":1,"halfBaths":4,"area":7953,"minStay":5,"pricePerNight":535,"totalPrice":9390,"rating":4},
{"title":"Twitterwire","sleeps":9,"bedRooms":5,"bathRooms":1,"halfBaths":4,"area":8779,"minStay":5,"pricePerNight":386,"totalPrice":9834,"rating":5},
{"title":"Topiczoom","sleeps":5,"bedRooms":4,"bathRooms":3,"halfBaths":1,"area":7951,"minStay":2,"pricePerNight":509,"totalPrice":9502,"rating":2},
{"title":"LiveZ","sleeps":4,"bedRooms":5,"bathRooms":4,"halfBaths":5,"area":8984,"minStay":2,"pricePerNight":601,"totalPrice":6193,"rating":1},
{"title":"Fliptune","sleeps":12,"bedRooms":3,"bathRooms":2,"halfBaths":5,"area":9563,"minStay":3,"pricePerNight":509,"totalPrice":7673,"rating":5},
{"title":"Brightdog","sleeps":11,"bedRooms":4,"bathRooms":2,"halfBaths":2,"area":8965,"minStay":2,"pricePerNight":212,"totalPrice":3349,"rating":4},
{"title":"Tazz","sleeps":20,"bedRooms":1,"bathRooms":3,"halfBaths":2,"area":8157,"minStay":3,"pricePerNight":530,"totalPrice":4673,"rating":2},
{"title":"Realblab","sleeps":18,"bedRooms":1,"bathRooms":3,"halfBaths":5,"area":8935,"minStay":4,"pricePerNight":347,"totalPrice":6852,"rating":1},
{"title":"Yakitri","sleeps":17,"bedRooms":4,"bathRooms":1,"halfBaths":5,"area":8016,"minStay":5,"pricePerNight":556,"totalPrice":5338,"rating":5},
{"title":"Realpoint","sleeps":7,"bedRooms":4,"bathRooms":2,"halfBaths":3,"area":9251,"minStay":5,"pricePerNight":534,"totalPrice":6679,"rating":2},
{"title":"Twitterwire","sleeps":16,"bedRooms":2,"bathRooms":2,"halfBaths":3,"area":7681,"minStay":2,"pricePerNight":579,"totalPrice":8047,"rating":4},
{"title":"Twinder","sleeps":3,"bedRooms":2,"bathRooms":2,"halfBaths":4,"area":9383,"minStay":4,"pricePerNight":394,"totalPrice":8670,"rating":1},
{"title":"Jaxworks","sleeps":2,"bedRooms":3,"bathRooms":3,"halfBaths":2,"area":7850,"minStay":5,"pricePerNight":239,"totalPrice":7539,"rating":1},
{"title":"Mita","sleeps":13,"bedRooms":4,"bathRooms":2,"halfBaths":2,"area":9900,"minStay":4,"pricePerNight":361,"totalPrice":9951,"rating":2},
{"title":"Thoughtbeat","sleeps":9,"bedRooms":4,"bathRooms":2,"halfBaths":5,"area":8934,"minStay":3,"pricePerNight":522,"totalPrice":6858,"rating":3},
{"title":"Eayo","sleeps":14,"bedRooms":5,"bathRooms":4,"halfBaths":5,"area":7608,"minStay":3,"pricePerNight":297,"totalPrice":9074,"rating":5},
{"title":"Meezzy","sleeps":10,"bedRooms":4,"bathRooms":1,"halfBaths":5,"area":8436,"minStay":3,"pricePerNight":433,"totalPrice":8566,"rating":4},
{"title":"Dynabox","sleeps":5,"bedRooms":3,"bathRooms":4,"halfBaths":3,"area":7760,"minStay":5,"pricePerNight":315,"totalPrice":4909,"rating":1},
{"title":"Skipstorm","sleeps":9,"bedRooms":1,"bathRooms":2,"halfBaths":4,"area":7529,"minStay":3,"pricePerNight":625,"totalPrice":6816,"rating":5},
{"title":"Photobean","sleeps":1,"bedRooms":5,"bathRooms":4,"halfBaths":5,"area":7953,"minStay":3,"pricePerNight":247,"totalPrice":5602,"rating":5},
{"title":"Shufflebeat","sleeps":1,"bedRooms":4,"bathRooms":1,"halfBaths":2,"area":7849,"minStay":5,"pricePerNight":116,"totalPrice":9983,"rating":2},
{"title":"DabZ","sleeps":18,"bedRooms":3,"bathRooms":1,"halfBaths":2,"area":8778,"minStay":4,"pricePerNight":289,"totalPrice":9925,"rating":1},
{"title":"Flipbug","sleeps":15,"bedRooms":4,"bathRooms":2,"halfBaths":3,"area":9052,"minStay":3,"pricePerNight":548,"totalPrice":5906,"rating":3},
{"title":"Oyoloo","sleeps":3,"bedRooms":1,"bathRooms":2,"halfBaths":3,"area":8149,"minStay":2,"pricePerNight":139,"totalPrice":5020,"rating":2},
{"title":"Kayveo","sleeps":8,"bedRooms":2,"bathRooms":2,"halfBaths":3,"area":8372,"minStay":3,"pricePerNight":139,"totalPrice":5710,"rating":4},
{"title":"Brainbox","sleeps":18,"bedRooms":2,"bathRooms":1,"halfBaths":3,"area":7555,"minStay":2,"pricePerNight":657,"totalPrice":5484,"rating":1},
{"title":"Innotype","sleeps":9,"bedRooms":1,"bathRooms":3,"halfBaths":3,"area":7932,"minStay":3,"pricePerNight":541,"totalPrice":8869,"rating":5},
{"title":"Photojam","sleeps":5,"bedRooms":1,"bathRooms":4,"halfBaths":4,"area":8242,"minStay":5,"pricePerNight":326,"totalPrice":8304,"rating":1}]